Workbook

Sheet READ ME
A1: STUDENT RECONSTRUCTION - ILLUSTRATIVE ONLY
A3: This file is a graduate coursework reconstruction of a real transaction, built by Mason J. Bennett (M.S. Finance, University of Arkansas) from publicly available filings. It is not affiliated with any party to the actual transaction and is published solely as a work sample. Assumptions diverge from actual deal terms where figures were not public. Not investment advice.
A5: masonjbennett.com | bennettmasonj@gmail.com

Sheet Summary
A1: JAGEX LBO MODEL — EXECUTIVE DASHBOARD
A2: CVC Capital Partners + Haveli Investments | Acquisition from The Carlyle Group | 14-May-2024
A3: University of Arkansas — Mason Bennett, , | April 2026
A5: DEAL AT A GLANCE
A6: Deal Value (USD) | B6: 1136 | D6: PitchBook (T3); officially undisclosed
A7: Deal Value (GBP) | B7: 900 | D7: FT, Sky News, PE-Insights press leaks
A8: Implied EV (USD) | B8: 1087 | D8: Calc: Deal − Cash + Debt + Leases
A9: Pro Forma EBITDA (USD) | B9: 75 | D9: PitchBook PF (T3); $18.6M add-backs vs reported
A10: Reported TTM EBITDA (USD) | B10: 56.4 | D10: PitchBook + CH Jagex Ltd FY23 (T1 cross-check)
A11: Total New Debt (USD) | B11: 164.15 | D11: PitchBook only — lender ID/amounts ILLUSTRATIVE
A12: Sponsor Equity (USD) | B12: 971.85 | D12: Residual: deal value − debt
A13: Deal / PF EBITDA | B13: 15.1 | D13: Implied entry multiple
A15: RETURNS SUMMARY (5-year hold, 15x EV/EBITDA exit)
A16: Layer | B16: Base | C16: Upside | D16: Downside | E16: Notes
A17: Sponsor MOIC (gross, 15x exit) | B17: ='LBO Model'!C110 -> 1.5717798 | C17: ='LBO Model'!D131 -> 1.931403 | D17: ='LBO Model'!E131 -> 1.1337043 | E17: From LBO Model row 110 (Base) and rows 131 (scenarios). Pre-fund mechanics.
A18: Sponsor MOIC (post-MIP) | B18: ='LBO Model'!C111 -> 1.5717798 | C18: ='LBO Model'!D131 -> 1.931403 | D18: ='LBO Model'!E131 -> 1.1337043 | E18: 10% MIP × 2.0x MOIC vesting hurdle. Base case does NOT clear hurdle.
A19: Sponsor IRR (5yr, post-MIP) | B19: ='LBO Model'!C112 -> 0.094657713 | C19: ='LBO Model'!D132 -> 0.14070825 | D19: ='LBO Model'!E132 -> 0.025415684 | E19: Base case below typical 20% PE target — deal is conservative.
A20: LP net IRR (after fund mechanics) | B20: =IF(('LBO Model'!$C$130+'LBO Model'!$C$209-MAX(0,'LBO Model'!$C$130+'LBO Model'!$C$209-'LBO Model'!$C$210)*'LBO Model'!$C$201)<=0,"N/A",(('LBO Model'!$C$130+'LBO Model'!$C$209-MAX(0,'LBO Model'!$C$130+'LBO Model'!$C$209-'LBO Model'!$C$210)*'LBO Model'!$C$201)/'LBO Model'!$C$9)^(1/5)-1) -> 0.080288182 | C20: =IF(('LBO Model'!$D$130+'LBO Model'!$C$209-MAX(0,'LBO Model'!$D$130+'LBO Model'!$C$209-'LBO Model'!$C$210)*'LBO Model'!$C$201)<=0,"N/A",(('LBO Model'!$D$130+'LBO Model'!$C$209-MAX(0,'LBO Model'!$D$130+'LBO Model'!$C$209-'LBO Model'!$C$210)*'LBO Model'!$C$201)/'LBO Model'!$C$9)^(1/5)-1) -> 0.11957342 | D20: =IF(('LBO Model'!$E$130+'LBO Model'!$C$209-MAX(0,'LBO Model'!$E$130+'LBO Model'!$C$209-'LBO Model'!$C$210)*'LBO Model'!$C$201)<=0,"N/A",(('LBO Model'!$E$130+'LBO Model'!$C$209-MAX(0,'LBO Model'!$E$130+'LBO Model'!$C$209-'LBO Model'!$C$210)*'LBO Model'!$C$201)/'LBO Model'!$C$9)^(1/5)-1) -> 0.0066517695 | E20: After 2-and-20 fund mechanics. Base ~8% — right at the 8% preferred return threshold.
A22: RETURNS ATTRIBUTION (Base case, 15x Y5 exit)
A23: Driver | B23: £M | C23: % of Total | D23: Investment Implication
A24: EBITDA growth | B24: ='LBO Model'!C148 -> 320.3845 | C24: ='LBO Model'!C155 -> 0.73461302 | D24: CVC thesis is OPERATIONAL — three-quarters of value from EBITDA growth.
A25: Multiple change (15.2x → 15.0x) | B25: ='LBO Model'!C149 -> -16.257601 | C25: ='LBO Model'!C156 -> -0.037277227 | D25: Slight contraction. Multiple expansion would require richer 2029 exit market.
A26: Deleveraging | B26: ='LBO Model'!C150 -> 132 | C26: ='LBO Model'!C157 -> 0.3026642 | D26: TL fully repaid by Y5 — but only 30% of return given conservative 2.2x leverage.
A27: Total equity value created | B27: ='LBO Model'!C151 -> 436.1269 | C27: 100.0% | D27: Reconciles to Exit Equity − Entry Equity within rounding (LBO Model C152).
A29: VALUATION CROSS-METHOD ($M)
A30: Method | B30: Low | C30: Midpoint | D30: High | E30: Deal Reference | F30: Notes
A31: CCA — original 8 comps | B31: ='Football Field'!B5 -> 299 | C31: ='Football Field'!D5 -> 616 | D31: ='Football Field'!C5 -> 933 | E31: 1136 | F31: 25th-75th EV/EBITDA × $75M PF
A32: CCA — tight peer (PF basis) | B32: =CCA!C53 -> 517.5 | C32: =(CCA!C97+CCA!C53)/2 -> 556.9521 | D32: =CCA!C97 -> 596.4042 | E32: 1136 | F32: Paradox/Frontier/Everplay; trough vs PF
A33: PTA — original 6 deals | B33: ='Football Field'!B6 -> 374 | C33: ='Football Field'!D6 -> 779 | D33: ='Football Field'!C6 -> 1184 | E33: 1136 | F33: 25th-75th of original PitchBook set
A34: PTA — expanded set (live-service take-privates) | B34: ='Football Field'!B9 -> 1192.5 | C34: ='Football Field'!D9 -> 1353.75 | D34: ='Football Field'!C9 -> 1515 | E34: 1136 | F34: Carlyle/Jagex 2021 + landmark take-privates
A35: DCF (8-12% WACC, 1.5-3.5% TGR) | B35: ='Football Field'!B7 -> 585 | C35: ='Football Field'!D7 -> 939 | D35: ='Football Field'!C7 -> 1293 | E35: 1136 | F35: WACC build: CAPM derives ~10.0% (Damodaran Jan-2026 inputs)
A36: LBO (15-20% IRR, 15-18x exit) | B36: ='Football Field'!B8 -> 779 | C36: ='Football Field'!D8 -> 927.5 | D36: ='Football Field'!C8 -> 1076 | E36: 1136 | F36: Implied range from sponsor return targets
A38: DEAL PRICE | C38: $1,136M | E38: 1136 | F38: Officially undisclosed; PitchBook back-calc from press £910M
A40: WHERE TO LOOK — TAB & CELL REFERENCES
A41: To find... | B41: Tab | C41: Cells
A42: Deal vehicle structure (Janus chain) | B42: Deal Summary | C42: B89:D94
A43: Carlyle-era debt (CH charges 0004/0005) | B43: Deal Summary | C43: B96:D100
A44: Pro Forma EBITDA bridge ($75M) | B44: Historicals | C44: B138:D166
A45: Tight peer analysis (Paradox/Frontier/Everplay) | B45: CCA | C45: B48:D61
A46: Peer regression analysis | B46: CCA | C46: B64:D102 | D46: Slope, R², margin-adjusted multiples
A47: Live-service take-private precedents | B47: PTA | C47: B55:I81
A48: WACC build (CAPM) | B48: DCF | C48: B52:D69 | D48: Risk-free, ERP, beta, target capital structure
A49: Original LBO operating model
A50: Management Incentive Plan | B50: LBO Model | C50: B100:D113 | D50: 10% MIP, 2.0x hurdle, dilution math
A51: Operating scenarios (3 cases) | B51: LBO Model | C51: B116:F134 | D51: Base/Upside/Downside with Y5 returns
A52: Returns attribution waterfall | B52: LBO Model | C52: B137:D159 | D52: EBITDA growth / Multiple / Deleveraging
A53: Entry × Exit sensitivity | B53: LBO Model | C53: B162:I173 | D53: 6×7 MOIC matrix across multiples
A54: Exit EV-to-equity bridge | B54: LBO Model | C54: B176:D192 | D54: Refined exit mechanics with fees/escrow/cash
A55: PE fund waterfall (LP net) | B55: LBO Model | C55: B195:D225 | D55: 2-and-20 economics, gross-to-net comparison
A56: Football Field (cross-method) | B56: Football Field | C56: A4:F9 | D56: CCA, PTA (×2), DCF, LBO ranges
A57: All sources with Tier flags | B57: Source Log | C57: B33:G56 | D57: 20 Tier 1/2 entries with direct URLs
A60: KEY DEFENSIBILITY POINTS FOR Q&A
A61: "How do you know Carlyle paid $530M?" | B61: Inferred — flat to confirmed Macarthur 2020 price (PR Newswire). Marked ILLUSTRATIVE in Deal Summary C86 and LBO Model C78.
A62: "Did Carlyle run Jagex unlevered?" | B62: Opco yes (Jagex Ltd standalone), group no. Companies House charges 0004 (Lucid 2021) and 0005 (Kroll 2023) confirm holdco-level Carlyle-era debt. See Deal Summary B96:B100 and EV Bridge B23.
A63: "Why is your live-service PTA median (19.5x) so different from the broader gaming M&A median (13.1x)?" | B63: The expanded set focuses on (i) the seller precedent (Carlyle/Jagex 2021) and (ii) the four landmark live-service take-privates (Microsoft/Activision, Take-Two/Zynga, Sony/Bungie, EQT/Keywords). The broader gaming M&A set includes small-cap and distressed deals that distort the multiple range. See PTA tab rows 55-81.
A64: "Walk me through the $75M pro forma EBITDA." | B64: Built up in Historicals B138:B166. Six items totalling ~$18.6M of add-backs to bridge from reported $56.4M. Each item ILLUSTRATIVE (PitchBook does not enumerate). Haircut sensitivity shows 17.4x at 50% haircut, 20.1x at 100% rejection.
A65: "Where do your IRR returns come from?" | B65: Returns Attribution (LBO Model B137:B159): 73% EBITDA growth, -4% multiple change, 30% deleveraging. Operational thesis, not financial engineering.
A66: "What's the LP's net IRR?" | B66: Base case 7.7% — BELOW the 8% preferred return. GPs collect mgmt fees but no carry. PE Fund Waterfall LBO Model B195:B225.
A67: "Is the deal overpriced?" | B67: Depends on exit multiple. At 15x entry / 15x exit: 1.55x MOIC / 9.2% IRR (below typical PE target). 18x exit needed to clear 2.0x MIP hurdle. Entry × Exit sensitivity LBO Model B162:I173.
A68: "Is there a fairness opinion?" | B68: No. Private-to-private secondary buyout has no banker fairness opinion. Football Field is the cross-method reasonableness check.
A70: Jagex_LBO_DCF_Final.xlsx | University of Arkansas | April 2026

Sheet Deal Summary
B1: JAGEX LBO ANALYSIS — CVC/Haveli Acquisition
B2: Private-to-Private Secondary Buyout from Carlyle | Updated with PitchBook Data
B4: DEAL OVERVIEW (PitchBook Deal #6)
B5: Target | C5: Jagex Limited | D5: PitchBook; Carlyle PR Feb 9 2024
B6: HQ | C6: Cambridge, United Kingdom | D6: PitchBook Company Info
B7: Industry / SIC | C7: Entertainment Software / MMORPG | D7: PitchBook
B8: Financing Status | C8: Private Equity-Backed | D8: PitchBook Deal #6
B9: Business Status | C9: Generating Revenue | D9: PitchBook Deal #6
B10: CEO/Lead MGT (at deal) | C10: Philip Mansell (at deal); Jon Bellamy (from Mar 2025) | D10: PitchBook Deal #6; Jagex PR Mar 4 2025 (CEO transition)
B11: Employees | C11: 700 | D11: PitchBook Deal #6
B12: Flagship Product | C12: RuneScape + Old School RuneScape | D12: Jagex PR Feb 9 2024
B13: Lifetime Franchise Revenue | C13: $2 billion+ (updated Mar 2025) | D13: Jagex PR Mar 4 2025 ($1.5B+ at deal; $2B+ by Mar 2025)
B14: Active Subscribers | C14: 2.4 million | D14: Carlyle PR Feb 9 2024
B15: Lifetime Accounts | C15: 320+ million | D15: Carlyle PR Feb 9 2024
B17: TRANSACTION DETAILS (PitchBook)
B18: Deal Type | C18: Buyout/LBO, Secondary Buyout | D18: PitchBook Deal #6
B19: Announced Date | C19: 09-Feb-2024 | D19: PitchBook Deal #6
B20: Deal Date (Closed) | C20: 14-May-2024 | D20: PitchBook Deal #6
B21: Deal Status | C21: Completed | D21: PitchBook Deal #6
B22: Financing Source | C22: Private Equity | D22: PitchBook Deal #6
B23: Use of Proceeds | C23: Acquisition-related: LBO | D23: PitchBook Deal #6
B24: % Acquired | C24: 100.00% | D24: PitchBook Deal #6
B26: Buyer 1 | C26: CVC Capital Partners (Fund VIII) | D26: PitchBook Investors; Lead: Nicholas Clarry
B27: Buyer 2 | C27: Haveli Investments | D27: PitchBook Investors; Lead: Brian Sheth
B28: Seller | C28: The Carlyle Group (Full Exit) | D28: PitchBook Sellers/Exiters
B29: Seller Funds | C29: Carlyle Partners VII + Carlyle Europe Tech Partners IV | D29: PitchBook Sellers/Exiters
B30: % Company Sold | C30: 100.00% | D30: PitchBook Sellers/Exiters
B32: ADVISORS (PitchBook)
B33: Goldman Sachs | C33: Advisor: General — CVC Capital Partners | D33: PitchBook Advisors #1
B34: Goldman Sachs | C34: Advisor: General — Haveli Investments | D34: PitchBook Advisors #2
B35: Aream & Co. | C35: Advisor: General — Jagex (Seller-side) | D35: PitchBook Advisors #3
B36: Liberty Corporate Finance | C36: Advisor: General — Jagex | D36: PitchBook Advisors #4
B37: Morgan Stanley | C37: Advisor: General — Jagex | D37: PitchBook Advisors #5
B38: Apollo Global Mgmt | C38: Debt Financing — Jagex | D38: PitchBook Advisors #6
B39: Oaktree Capital Mgmt | C39: Debt Financing — Jagex | D39: PitchBook Advisors #7
B40: Latham & Watkins | C40: Legal Advisor — CVC (Lead: Suneel Basson-Bhatoa) | D40: PitchBook Advisors #8
B41: Kirkland & Ellis | C41: Legal Advisor — Carlyle (Lead: David Higgins) | D41: PitchBook Advisors #9
B43: DEAL VALUATION METRICS (PitchBook + Press)
B44: Deal Amount (USD) | C44: $1,136M | D44: PitchBook Deal #6: $1,136,109K
B45: Post Valuation (USD) | C45: $1,136M | D45: PitchBook Deal #6
B46: Implied Enterprise Value (USD) | C46: $1,087M | D46: PitchBook Deal #6: $1,086,869K
B47: GBP/USD at Deal Close (May 2024) | C47: 1.2627 | D47: X-Rates.com: May 2024 avg
B48: Deal Amount (GBP) | C48: £900M | D48: Calc: $1,136M / 1.2627 = £900M (press reported £910M)
B49: Implied EV (GBP) | C49: £861M | D49: Calc: $1,087M / 1.2627 = £861M
B51: Pro Forma EBITDA (Reported by PitchBook) | C51: $75.00M (£59.4M) | D51: PitchBook Deal #6: "Pro Forma EBITDA (Reported) 75.00"
B52: TTM Reported EBITDA (Dec 2023) | C52: $56.4M (£44.4M) | D52: PitchBook Financials TTM Dec 2023
B54: Deal Size / EBITDA (reported) | C54: 20.13x | D54: PitchBook Deal Multiples
B55: Deal Size / Revenue | C55: 6.02x | D55: PitchBook Deal Multiples
B56: Implied EV / EBITDA (reported) | C56: 19.25x | D56: PitchBook Deal Multiples
B57: Implied EV / Revenue | C57: 5.76x | D57: PitchBook Deal Multiples
... B60: Deal Amount / Pro Forma EBITDA | C60: 15.1x | D60: Calculated: $1,136M / $75M = 15.1x; corroborated by Naavik up to 15x
B62: OWNERSHIP HISTORY & SELLER RETURN
B63: Insight Venture Partners | C63: 2005-2016 | D63: Wikipedia
B64: Hongtou / Fukong (China) | C64: 2016-2020 | D64: Wikipedia
B65: Macarthur Fortune Holding | C65: 2020 ($530M) | D65: Wikipedia; Game Developer
B66: The Carlyle Group | C66: Jan 2021 – May 2024 (~$530M entry) | D66: Carlyle PR; Wikipedia; Telegraph
B67: CVC + Haveli | C67: May 2024 – Present ($1.14B / £910M) | D67: PitchBook; Wikipedia
B69: Carlyle Entry (~Jan 2021) | C69: ~$530M (~£385M at prevailing FX) | D69: Telegraph; Wikipedia; multiple sources
B70: Carlyle Exit (May 2024) | C70: $1,136M (£900M) | D70: PitchBook Deal #6: $1,136,109K
B71: Carlyle Holding Period | C71: ~3.3 years | D71: Calculated: Jan 2021 → May 2024
B72: Carlyle Implied MOIC | C72: ~2.14x | D72: $1,136M / $530M = 2.14x
B73: Carlyle Implied IRR | C73: ~26% | D73: 2.14^(1/3.3) - 1 = 25.5%
B75: POST-DEAL DEVELOPMENTS
B76: CEO Transition | C76: Jon Bellamy replaced Phil Mansell (Mar 4 2025) | D76: Jagex PR Mar 4 2025; Bellamy was CVC advisor pre-appointment
B77: Pipeworks Divestiture | C77: Sold to Virtuos Studios (post-acquisition) | D77: Wikipedia; acquired Jul 2022, later divested
B78: Lifetime Franchise Revenue | C78: Updated to $2 billion+ (from $1.5B+ at deal) | D78: Jagex PR Mar 4 2025
B79: RuneScape: Dragonwilds | C79: New co-op survival game launched Apr 2025 (Steam EA) | D79: Wikipedia
B82: SOURCE-CONFIDENCE NOTES
B83: Deal value precision flag | C83: $1,136M is INFERRED — official terms not disclosed | D83: Tier 3-4: Trade press £910M (FT, Sky News, PE-Insights pre-announce); PitchBook $1,136,109K is back-calc
B84: CVC vs Haveli equity split | C84: NOT DISCLOSED — both sponsors named jointly | D84: Market intuition: CVC majority, Haveli minority co-investor (typical pattern)
B85: Lender identities & amounts | C85: Apollo / Oaktree / Permira amounts are PitchBook only — uncorroborated | D85: Companies House Janus Bidco MR01 (25 Apr 2024, 40pp) is paid PDF — paths to T1 verification
B86: Carlyle 2021 entry value ($530M) | C86: INFERRED — flat to Macarthur 2020 confirmed price | D86: Macarthur $530M confirmed: prnewswire.com/news-releases/platinum-fortune-acquires-jagex-for-530-million-301050848.html
B89: DEAL VEHICLE STRUCTURE (Companies House — Tier 1)
B90: Janus UK Topco Ltd (Jersey) | C90: CH FC041396 | Inc 13-Mar-2024 | Sponsor-level holdco | D90: Directors: Jennifer E. Lambkin, Abiola M. Motajo (Mourant sec)
B91: Janus Holdco Limited | C91: Group-level UK holdco | Files consolidated accounts | D91: Most material post-LBO disclosure (acquisition goodwill, debt notes)
B92: Janus Midco Limited | C92: CH #15451988 | Inc 30-Jan-2024 | Intermediate holdco
B93: Janus Bidco Limited | C93: CH #15451932 | Inc 30-Jan-2024 | DIRECT PARENT of Jagex Ltd | Carries debt | D93: MR01 charge filed 29-Apr-2024 (40pp); SH01 share allotment 14-May-2024 in USD
B94: Jagex Limited (operating co.) | C94: CH #03982706 | Inc Apr 2000 | UK opco
B96: CARLYLE-ERA DEBT (Companies House Charges Register)
B97: Charge 0004 | C97: Lucid Trustee Services | Created 7-May-2021 | Satisfied 15-May-2024 | D97: Documents Carlyle 2021 acquisition financing at the holdco level
B98: Charge 0005 | C98: Kroll Trustee Services | Created 20-Jun-2023 | Satisfied 15-May-2024
B99: Charge 0006 | C99: Kroll Trustee Services | Created 10-Sep-2024 | OUTSTANDING
B100: Note: At the operating-company level (Jagex Ltd #03982706), funded debt was zero throughout the Carlyle hold period. At the corporate-group level (June UK Bidco / June UK Finco), Carlyle-era acquisition debt was secured under charge 0004 (Lucid Trustee, May 2021) and refinanced/upsized under charge 0005 (Kroll Trustee, June 2023). Both charges were satisfied at deal close on 15 May 2024 as part of the CVC/Haveli refinancing.

Sheet EV Bridge
B1: JAGEX — ENTERPRISE VALUE BRIDGE
B2: Private-to-Private: No share price mechanics. EV derived from deal structure.
B3: ($ in thousands, per PitchBook)
B5: EV BRIDGE RECONCILIATION
B6: Deal Amount (Equity Value paid by CVC/Haveli) | C6: 1136109 | D6: PitchBook Deal #6: "Deal Size: 1,136,109.21"
B7: (-) Target Cash & Equivalents (FY2023) | C7: -50239 | D7: PitchBook BS: Cash & CE at 31-Dec-2023
B8: (+) Target Total Debt (FY2023) | C8: 0 | D8: PitchBook BS: Total Debt = $0 (zero funded debt)
B9: (+) Capital Lease Obligations | C9: 2238 | D9: PitchBook BS: Current cap lease $2,238K (FY2023)
B10: (-) Short-Term Investments | C10: 0 | D10: PitchBook BS: none reported FY2023
B12: Implied Enterprise Value (calculated) | C12: =SUM(C6:C10) -> 1088108 | D12: Deal Amount - Cash + Debt + Leases
B13: Implied Enterprise Value (PitchBook) | C13: 1086869 | D13: PitchBook Deal #6: "Implied EV: 1,086,869.49"
B15: Reconciliation Check | C15: =C12-C13 -> 1239 | D15: Calculated vs PitchBook
B18: NOTES ON PRIVATE-TO-PRIVATE EV BRIDGE
B19: Unlike public-to-private deals, there is no (Price x Shares) calculation. The Deal Amount IS the equity value paid.
B20: PitchBooks Implied EV ($1,086,869K) = Deal Amount ($1,136,109K) minus adjustments for cash, debt, and other items.
B21: The ~$49M difference between Deal Amount and Implied EV is primarily the targets cash balance ($50,239K), net of minor lease adjustments.
B22: Reconciliation difference (if any) reflects rounding or items PitchBook includes that are not individually disclosed (e.g., minority interests, pension adjustments).
B23: Note: At the OPCO level (Jagex Ltd #03982706) there was no funded debt under Carlyle 2021-2024 — accurate per Companies House Jagex Ltd accounts. However, the GROUP (June UK Bidco / June UK Finco) carried debt secured by Companies House charges 0004 (Lucid Trustee, 7 May 2021) and 0005 (Kroll Trustee, 20 Jun 2023), both satisfied at deal close 15 May 2024. The CVC/Haveli acquisition financing (~$164M per PitchBook) is now secured at Janus Bidco level (charge 0006, 10 Sep 2024, Kroll Trustee).

Sheet Historicals
B1: JAGEX LIMITED — HISTORICAL FINANCIALS (PitchBook)
B2: Amounts in $000s USD (PitchBook) | Source: PitchBook Data, Inc. | All data "Original" per PitchBook
B3: Downloaded 15-Apr-2026 for Mason Bennett, University of Arkansas (Students)
B5: INCOME STATEMENT
C6: FY2019 | D6: FY2020 | E6: FY2021 | F6: FY2022 | G6: FY2023 | H6: FY2024 | I6: Source
B7: Year End | C7: 31-Dec-2019 | D7: 31-Dec-2020 | E7: 31-Dec-2021 | F7: 31-Dec-2022 | G7: 31-Dec-2023 | H7: 31-Dec-2024
B8: Total Revenue | C8: 138511 | D8: 153772 | E8: 171704 | F8: 169367 | G8: 188773 | H8: 193483 | I8: PitchBook IS (Jagex Limited consolidated group: Jagex + Pipeworks + Gamepires); may differ from Jagex Ltd standalone filings at Companies House. FY19 derived from CoR+GP.
B9: Cost of Revenue | C9: 49900 | D9: 16924 | E9: 22539 | F9: 20751 | G9: 27518 | H9: 27313 | I9: PitchBook IS
B10: Gross Profit | C10: 88611 | D10: 136848 | E10: 149164 | F10: 148616 | G10: 161255 | H10: 166170 | I10: PitchBook IS
B12: Wages & Salaries | C12: - | D12: 40432 | E12: 39951 | F12: 35716 | G12: 40678 | H12: 44360 | I12: PitchBook IS
B13: Directors' Remuneration | C13: 7301 | D13: 5467 | E13: 6406 | F13: 4647 | G13: 4095 | H13: 3176 | I13: PitchBook IS
B14: Auditor Fees | C14: 153 | D14: 95 | E14: 1369 | F14: 1352 | G14: 587 | H14: 825 | I14: PitchBook IS
B15: Depreciation | C15: - | D15: 2072 | E15: 2590 | F15: 2243 | G15: 3336 | H15: 3125 | I15: PitchBook IS
B16: D&A (incl amort) | C16: 2129 | D16: 2129 | E16: 4185 | F16: 10482 | G16: 9009 | H16: 8136 | I16: PitchBook IS
B17: Total Opex (incl CoR) | C17: - | D17: 103754 | E17: 120819 | F17: 126677 | G17: 141335 | H17: 163270 | I17: PitchBook IS
B19: Total Operating Profit/(Loss) | C19: 58308 | D19: 50018 | E19: 50884 | F19: 42690 | G19: 47438 | H19: 30213 | I19: PitchBook IS
B21: Interest Expense | C21: - | D21: 353 | E21: 322 | F21: 291 | G21: 4761 | H21: 2451 | I21: PitchBook IS
B22: Interest Income | C22: 540 | D22: 64 | E22: 21 | F22: 2994 | G22: 6143 | H22: 10535 | I22: PitchBook IS
B23: Net Interest (Income)/Expense | C23: - | D23: 288 | E23: 301 | F23: -2703 | G23: -1383 | H23: -8084 | I23: PitchBook IS; negative=net income
B25: Pretax Income | C25: 49730 | D25: 49730 | E25: 50583 | F25: 45393 | G25: 48820 | H25: 38297 | I25: PitchBook IS
B26: Provision for Income Tax | C26: 5233 | D26: 5890 | E26: 2285 | F26: -1522 | G26: -102 | H26: 2735 | I26: PitchBook IS
B28: Net Income to Common | C28: 43840 | D28: 43840 | E28: 48298 | F28: 46915 | G28: 48922 | H28: 35562 | I28: PitchBook IS
B30: Profitability Metrics:
B31: EBITDA | C31: - | D31: 52147 | E31: 55069 | F31: 53172 | G31: 56447 | H31: 38349 | I31: PitchBook IS
B32: EBIT | C32: - | D32: 50018 | E32: 50884 | F32: 42690 | G32: 47438 | H32: 30213 | I32: PitchBook IS
B33: Gross Dividends | C33: 97492 | D33: 0 | E33: 16612 | F33: 0 | G33: 2953 | H33: 0 | I33: PitchBook IS
B35: KEY MARGINS & GROWTH (PitchBook Ratios)
B36: Gross Margin | C36: - | D36: 0.8899 | E36: 0.8687 | F36: 0.8775 | G36: 0.8542 | H36: 0.8588 | I36: PitchBook Ratios
B37: EBITDA Margin | C37: - | D37: 0.3391 | E37: 0.3207 | F37: 0.3139 | G37: 0.299 | H37: 0.1982 | I37: PitchBook Ratios
B38: EBIT Margin | C38: - | D38: 0.3253 | E38: 0.2963 | F38: 0.2521 | G38: 0.2513 | H38: 0.1562 | I38: PitchBook Ratios
B39: Net Profit Margin | C39: - | D39: 0.285 | E39: 0.2813 | F39: 0.277 | G39: 0.2592 | H39: 0.1838 | I39: PitchBook Ratios
B41: Revenue % Growth (GBP basis) | C41: - | D41: - | E41: 0.0409 | F41: 0.1006 | G41: 0.1051 | H41: -0.0029 | I41: PitchBook Ratios
B42: EBITDA % Growth | C42: - | D42: - | E42: -0.0156 | F42: 0.0773 | G42: 0.0526 | H42: -0.3391 | I42: PitchBook Ratios
B44: Effective Tax Rate | C44: - | D44: 0.1185 | E44: 0.0452 | F44: -0.0335 | G44: -0.0021 | H44: 0.0714 | I44: Calculated: Tax/Pretax. Low rates reflect UK Video Games Tax Relief (VGTR)
B47: BALANCE SHEET
C48: FY2019 | D48: FY2020 | E48: FY2021 | F48: FY2022 | G48: FY2023 | H48: FY2024 | I48: Source
B49: Assets:
B50: Cash & Equivalents | C50: 19507 | D50: 60445 | E50: 61599 | F50: 35465 | G50: 50239 | H50: 27250 | I50: PitchBook BS
B51: Trade/Accts Receivable | C51: - | D51: - | E51: - | F51: - | G51: - | H51: -
B52: Other Current Assets | C52: 16497 | D52: 35150 | E52: 45470 | F52: 88423 | G52: - | H52: 147068 | I52: PitchBook BS
B53: Total Current Assets | C53: 36492 | D53: 76942 | E53: 96748 | F53: 80935 | G53: 138662 | H53: 174318 | I53: PitchBook BS
B54: Net PP&E | C54: 8415 | D54: 8415 | E54: 8440 | F54: 6547 | G54: 4753 | H54: 2489 | I54: PitchBook BS
B55: Net Intangible Assets | C55: 10601 | D55: 10601 | E55: 20135 | F55: 19937 | G55: 28603 | H55: 38274 | I55: PitchBook BS
B56: Total Non-Current Assets | C56: 8424 | D56: 21843 | E56: 36009 | F56: 97595 | G56: 97912 | H56: 82672 | I56: PitchBook BS
B57: Total Assets | C57: - | D57: 98785 | E57: 132757 | F57: 178530 | G57: 236574 | H57: 256990 | I57: PitchBook BS
B59: Liabilities:
B60: Trade Payables | C60: 925 | D60: 1151 | E60: 27816 | F60: 24422 | G60: 27391 | H60: 28295 | I60: PitchBook BS
B61: Capital Lease Oblig. (Current) | C61: - | D61: 1172 | E61: 3573 | F61: 13409 | G61: 2238 | H61: 958 | I61: PitchBook BS
B62: Other Current Liabilities | C62: 31713 | D62: 44389 | E62: 12557 | F62: 15583 | G62: 23065 | H62: 15192 | I62: PitchBook BS
B63: Total Current Liabilities | C63: 31713 | D63: 46712 | E63: 43946 | F63: 53414 | G63: 52693 | H63: 44445 | I63: PitchBook BS
B64: LT Debt & Capital Lease | C64: - | D64: 2261 | E64: 2671 | F64: 2169 | G64: 2427 | H64: 2696 | I64: PitchBook BS
B65: Total Non-Current Liabilities | C65: 7376 | D65: 18669 | E65: 22716 | F65: 19277 | G65: 16946 | H65: 8143 | I65: PitchBook BS
B66: Total Liabilities | C66: - | D66: 65381 | E66: 66662 | F66: 72692 | G66: 69639 | H66: 52589 | I66: PitchBook BS
B68: Equity:
B69: Total Equity | C69: - | D69: 33404 | E69: 66095 | F69: 105838 | G69: 166935 | H69: 204402 | I69: PitchBook BS
B71: Financial Health:
B72: Total Debt | C72: 0 | D72: 0 | E72: 0 | F72: 0 | G72: 0 | H72: 0 | I72: PitchBook BS (no funded debt pre-deal)
B73: Net Debt | C73: 0 | D73: 0 | E73: 0 | F73: 0 | G73: 0 | H73: 0 | I73: PitchBook BS
B74: Working Capital | C74: 4779 | D74: 30230 | E74: 52802 | F74: 27520 | G74: 85969 | H74: 129873 | I74: PitchBook BS
B75: Capital Lease Obligations | C75: - | D75: 1172 | E75: 3573 | F75: 13409 | G75: 2238 | H75: 958 | I75: PitchBook BS
B78: KEY RATIOS (PitchBook)
B79: Current Ratio | C79: 2.13 | D79: 1.15 | E79: 1.65 | F79: 2.2 | G79: 1.52 | H79: 2.63 | I79: PitchBook Ratios
B80: Quick Ratio | C80: - | D80: - | E80: 0.35 | F80: 0.8 | G80: 0.85 | H80: 1.68 | I80: PitchBook Ratios
B81: Debt to Equity | C81: 0 | D81: 0 | E81: 0 | F81: 0 | G81: 0 | H81: 0 | I81: PitchBook Ratios
B82: Total Debt to EBITDA | C82: 0 | D82: 0 | E82: 0 | F82: 0 | G82: 0 | H82: 0 | I82: PitchBook Ratios
B83: Interest Coverage | C83: - | D83: 141.85 | E83: 157.8 | F83: 146.77 | G83: 9.96 | H83: 12.33 | I83: PitchBook Ratios
B84: EBITDA Interest Coverage | C84: - | D84: 147.88 | E84: 170.77 | F84: 182.81 | G84: 11.86 | H84: 15.65 | I84: PitchBook Ratios
B85: CapEx to Sales | C85: 0 | D85: 0 | E85: 0 | F85: 0 | G85: 0 | H85: 0 | I85: PitchBook Ratios
B86: Equity Multiplier | C86: - | D86: 2.96 | E86: 2.01 | F86: 1.69 | G86: 1.42 | H86: 1.26 | I86: PitchBook Ratios
B87: Sales per Employee | C87: - | D87: - | E87: - | F87: - | G87: - | H87: - | I87: PitchBook Ratios
B89: Employees | C89: 337 | D89: - | E89: - | F89: - | G89: - | H89: - | I89: PitchBook Ratios
B92: DEAL FINANCIALS AT CLOSE (PitchBook Deal #6)
B93: Deal Date | C93: 14-May-2024 | I93: PitchBook Deal #6, Buyout/LBO
B94: Valuation ($000s) | C94: 1136109 | I94: PitchBook Deal #6, Buyout/LBO
B95: Deal Size ($000s) | C95: 1136109 | I95: PitchBook Deal #6, Buyout/LBO
B96: Debt Raised ($000s) | C96: 164146 | I96: PitchBook Deal #6, Buyout/LBO
B97: Revenue ($000s) | C97: 188773 | I97: PitchBook Deal #6, Buyout/LBO
B98: EBITDA ($000s) | C98: 56447 | I98: PitchBook Deal #6, Buyout/LBO
B99: EBIT ($000s) | C99: 47438 | I99: PitchBook Deal #6, Buyout/LBO
B100: Net Income ($000s) | C100: 48922 | I100: PitchBook Deal #6, Buyout/LBO
B101: Implied EV ($000s) | C101: 1086869 | I101: PitchBook Deal #6, Buyout/LBO
B103: Valuation / EBITDA | C103: 20.13x | I103: PitchBook Deal #6, Buyout/LBO
B104: Valuation / Revenue | C104: 6.02x | I104: PitchBook Deal #6, Buyout/LBO
B105: Implied EV / EBITDA | C105: 19.25x | I105: PitchBook Deal #6, Buyout/LBO
B106: Implied EV / Revenue | C106: 5.76x | I106: PitchBook Deal #6, Buyout/LBO
B107: Debt Raised / EBITDA | C107: 2.91x | I107: PitchBook Deal #6, Buyout/LBO
B110: KEY OBSERVATIONS FOR MODELING
B111: FY2019 revenue not directly reported by PitchBook; derived as CoR ($49.9M) + GP ($88.6M) = $138.5M ≈ £108.6M (matches Companies House/Naavik)
B112: ZERO funded debt across entire history (FY2019-FY2023). All liabilities are trade payables, lease obligations, and other operating items.
B113: CapEx to Sales = 0.00% per PitchBook — Jagex capitalizes game development costs as intangibles, not PP&E. Intangibles grew from $10.6M to $28.6M (FY2019→FY2023).
B114: D&A jumped from $2.1M (FY2019-20) to $10.5M (FY2022) as intangible amortization from Pipeworks/Gamepires acquisitions kicked in.
B115: FY2022 revenue dipped in USD ($169M vs $172M FY2021) but grew 10.06% in GBP — pure FX effect (GBP weakened significantly in 2022).
B116: FY2024 shows significant margin compression: EBITDA margin fell from 29.9% to 19.8%, operating profit dropped 36%. Post-CVC acquisition investment phase.
B117: Working capital surged from $27.5M (FY2022) to $86.0M (FY2023) then $129.9M (FY2024) — cash accumulation under new ownership.
B118: Interest income grew from $21K (FY2021) to $10.5M (FY2024) reflecting high cash balances + high interest rate environment.
B119: Pro Forma EBITDA at deal ($75M per PitchBook) vs Reported EBITDA ($56.4M UK GAAP, pre-adjustments) implies ~$18.6M in PE-standard add-backs (non-recurring costs, deal expenses). Reuters Sep-2023 report of ~£60M pre-deal EBITDA (≈$76M at deal-time FX) aligns with the PF figure, indicating Reuters was reporting adjusted/run-rate EBITDA rather than UK GAAP reported.
B120: Gross margin very stable: 85-89% across all years. Virtually all margin volatility comes from operating expenses (wages, amortization).
B122: DATA QUALITY FLAG — FY2019
... B139: The valuation rests on a Pro Forma EBITDA of $75M (PitchBook "Pro Forma EBITDA (Reported)"). PitchBook does not disclose the specific add-backs bridging Reported TTM EBITDA ($56.4M) to Pro Forma ($75M). This is an $18.6M / 33% adjustment that materially affects the entry multiple (20.1x reported vs 15.1x PF). The bridge below reconstructs likely add-back items from PitchBook line items plus standard PE add-back conventions for a 2024 sponsor-secondary in UK gaming. Individual items are illustrative; the aggregate $18.6M reconciles to PitchBook's stated PF EBITDA within rounding.
B141: Bridge item | C141: $M | D141: Source / Rationale
...

Sheet CCA
B1: JAGEX — COMPARABLE COMPANY ANALYSIS (CCA)
B2: PitchBook Data, Inc. | Downloaded 15-Apr-2026 | All amounts in USD millions
B3: Created for: Mason Bennett, University of Arkansas (Students)
B5: FINANCIALS (TTM) | C5: Jagex | D5: Square Enix | E5: NCsoft | F5: Stillfront | G5: Gravity | H5: Pearl Abyss | I5: Paradox Int. | J5: Everplay | K5: Frontier Dev | L5: Source
B6: Ticker | C6: Private | D6: TKS:9684 | E6: KRX:036570 | F6: STO:SF | G6: NAS:GRVY | H6: KRX:263750 | I6: STO:PDX | J6: LON:EVPL | K6: LON:FDEV | L6: PitchBook
B7: Revenue ($M) | C7: 193.5 | D7: 2014.6 | E7: 1058.9 | F7: 582.4 | G7: 393.9 | H7: 256.9 | I7: 223.1 | J7: 218.6 | K7: 134.9 | L7: PitchBook TTM
B8: Revenue Growth % | C8: -0.003 | D8: -0.12 | E8: -0.045 | F8: -0.153 | G8: 0.119 | H8: 0.068 | I8: -0.004 | J8: -0.004 | K8: 0.158
B9: EBITDA ($M) | C9: 38.3 | D9: 314.4 | E9: 354.8 | F9: -62.2 | G9: 63.9 | H9: 5.4 | I9: 98.7 | J9: 85.9 | K9: 52.6 | L9: PitchBook TTM
B10: Norm. EBITDA Margin | C10: 0.198 | D10: 0.183 | E10: 0.06 | F10: 0.365 | G10: 0.171 | H10: 0.017 | I10: 0.443 | J10: 0.292 | K10: 0.369
B11: Net Income ($M) | C11: 35.6 | D11: 152.1 | E11: N/A | F11: -244 | G11: 47.4 | H11: N/A | I11: 12.8 | J11: 35.9 | K11: 26.2
B12: CapEx / Sales | C12: 0 | D12: 0.028 | E12: 0.076 | F12: 0.091 | G12: 0.011 | H12: 0.012 | I12: 0.299 | J12: 0.288 | K12: 0.279
B14: TRADING MULTIPLES (16-Apr-2026)
B15: EV / Revenue | D15: 2.13 | E15: 1.99 | F15: 1.1 | G15: N/A | H15: 8.26 | I15: 5.63 | J15: 2.02 | K15: 1.12 | L15: PitchBook
B16: EV / EBITDA (Normalized) | D16: 11.64 | E16: 33.02 | F16: 3.02 | G16: N/A | H16: 477.24 | I16: 12.72 | J16: 6.9 | K16: 3.03 | L16: PitchBook; Pearl Abyss 477x excluded as outlier
B17: Price / Revenue | D17: 2.88 | E17: 3.08 | F17: 0.42 | G17: 1.07 | H17: 9.36 | I17: 6.22 | J17: 2.32 | K17: 1.51
B18: Price / Earnings | D18: 16.87 | E18: 117.25 | F18: 22.25 | G18: 8.43 | H18: N/A | I18: 109.35 | J18: 10.38 | K18: 8.47
B20: SUMMARY STATISTICS
C21: EV / Revenue | D21: EV / EBITDA | E21: Notes
C22: (7 comps) | D22: (6 comps, excl. Pearl Abyss 477x)
B23: Mean | C23: 3.1785714 | D23: 11.721667
B24: Median | C24: 2.02 | D24: 9.27
B25: 25th Percentile | C25: 1.555 | D25: 3.9975
B26: 75th Percentile | C26: 3.88 | D26: 12.45
B28: IMPLIED JAGEX VALUATION ($M)
C29: EV/Revenue | D29: EV/EBITDA (Rptd) | E29: EV/EBITDA (PF $75M)
B30: 25th Percentile | C30: 300.8925 | D30: 153.10425 | E30: 299.8125
B31: Median | C31: 390.87 | D31: 355.041 | E31: 695.25
B32: Mean | C32: 615.05357 | D32: 448.93983 | E32: 879.125
B33: 75th Percentile | C33: 750.78 | D33: 476.835 | E33: 933.75
B35: Deal Price for Reference | C35: 1136 | D35: 1136 | E35: 1136 | F35: PitchBook: $1,136M deal amount (precise: $1,136,109K)
B36: Deal / PF EBITDA Multiple | E36: 15.2x | F36: $1,136M / $75M pro forma = 15.1x
B38: INTERPRETATION
B39: CCA implies Jagex standalone public trading value of $212M-$832M (EV/Revenue) or $227M-$874M (EV/EBITDA on pro forma).
B40: Deal price of $1.14B represents a significant premium to public comps — expected for a take-private LBO.
B41: Premium to CCA median: ~190% (EV/Revenue) and ~63% (EV/PF EBITDA). Consistent with significant control premium for PE take-private.
B42: Pearl Abyss excluded from EV/EBITDA due to near-zero EBITDA ($5.4M) creating extreme 477x outlier.
B43: Gravity missing EV/Revenue in PitchBook — GRVY trades OTC with limited liquidity.
B44: NCsoft EV/EBITDA of 33x reflects Lineage mobile franchise premium; excluding NCsoft, median drops to ~8.0x.
B45: Note: TTM financials reflect period ending ~Dec 2025, NOT deal-time (May 2024). EBITDA has declined from deal-time $56.4M to $38.3M.
B48: TIGHT PEER SUBSET (Paradox + Frontier + Everplay)
B49: Rationale: of the 8 PitchBook comps, the 3 closest to Jagex on (a) scale (~$200M revenue), (b) live-service / evergreen IP business model, (c) UK/EU geography, are: Paradox Interactive (DLC + grand strategy), Frontier Developments (Cambridge UK, sim), Everplay/Team17 (UK indie publisher). Square Enix and NCsoft are 5-10x larger and have different competitive dynamics. Pearl Abyss correctly excluded. Stillfront is mobile-distressed.
B51: Tight Peer EV/Revenue (Paradox, Everplay, Frontier) | C51: =MEDIAN(I15,J15,K15) -> 2.02
B52: Tight Peer EV/EBITDA (Paradox, Everplay, Frontier) | C52: =MEDIAN(I16,J16,K16) -> 6.9
B53: Implied Jagex EV (tight, EV/EBITDA × PF $75M) | C53: =C52*75 -> 517.5 | D53: Implied EV ($M)
B55: FORWARD-EBITDA BASIS (when LTM is a trough year)
B56: Jagex FY24 reported EBITDA ($38.3M) declined ~32% from FY23 ($56.4M) — clearly a trough. Applying peer multiples to a trough-year EBITDA understates fair value. Apply tight-peer median to FY+1 forward EBITDA from the DCF model.
B57: FY+1 (FY2025E) Forward EBITDA from DCF (£M) | C57: =DCF!D22 -> 69.51744
B58: FY+1 Forward EBITDA in USD (× FX 1.2627) | C58: =C57*1.2627 -> 87.779671
B59: Implied EV (Tight Peer EV/EBITDA × FY25E EBITDA, $M) | C59: =C52*C58 -> 605.67973 | D59: Forward-basis EV (more defensible than LTM trough)
B61: Deal Reference: $1,136M deal amount → comparison | C61: =1136-C59 -> 530.32027 | D61: Deal premium over tight-peer × FY+1 EBITDA implied EV ($M)
B64: PEER REGRESSION (Multiple vs Growth & Margin)
B65: Damodaran-style relative valuation: rather than applying a blunt median multiple, regress EV/EBITDA (or EV/Revenue) on peer-level growth rates and EBITDA margins, then apply the fitted relationship to Jagex's characteristics to derive a FAIR multiple. Tight peer set (Paradox, Everplay, Frontier) is too small for full regression (n=3); approach below computes a simple characteristic-adjusted multiple as a sensitivity.
B67: TIGHT PEER CHARACTERISTICS
B68: Peer | C68: Revenue ($M) | D68: Revenue Growth | E68: EBITDA Margin | F68: EV/Revenue | G68: EV/EBITDA
B69: Paradox Interactive | C69: =I7 -> 223.1 | D69: =I8 -> -0.004 | E69: =I10 -> 0.443 | F69: =I15 -> 5.63 | G69: =I16 -> 12.72
B70: Everplay Group | C70: =J7 -> 218.6 | D70: =J8 -> -0.004 | E70: =J10 -> 0.292 | F70: =J15 -> 2.02 | G70: =J16 -> 6.9
B71: Frontier Developments | C71: =K7 -> 134.9 | D71: =K8 -> 0.158 | E71: =K10 -> 0.369 | F71: =K15 -> 1.12 | G71: =K16 -> 3.03
B72: Jagex (target) | C72: =C7 -> 193.5 | D72: =C8 -> -0.003 | E72: =C10 -> 0.198 | F72: — private — | G72: — private —
B73: Peer averages | C73: =AVERAGE(C69:C71) -> 192.2 | D73: =AVERAGE(D69:D71) -> 0.05 | E73: =AVERAGE(E69:E71) -> 0.368 | F73: =AVERAGE(F69:F71) -> 2.9233333 | G73: =AVERAGE(G69:G71) -> 7.55
B75: SIMPLE REGRESSION: EV/EBITDA vs Revenue Growth
B76: Slope (Δ EV/EBITDA per 1pp Δ growth) | C76: =SLOPE(G69:G71,D69:D71) -> -41.851852 | D76: Positive slope = market pays up for growth
B77: Intercept (EV/EBITDA at 0% growth) | C77: =INTERCEPT(G69:G71,D69:D71) -> 9.6425926
B78: R-squared | C78: =RSQ(G69:G71,D69:D71) -> 0.64406138 | D78: With n=3, R² is not a rigorous fit statistic; use directionally only
B79: Predicted Jagex EV/EBITDA at Jagex growth rate | C79: =C77+C76*D72 -> 9.7681481 | D79: Regression predicted multiple applied to Jagex's growth
B80: Simple average EV/EBITDA of tight peers | C80: =G73 -> 7.55
B81: Margin-adjusted multiple (peer avg × Jagex/peer margin) | C81: =G73*(E72/E73) -> 4.0622283 | D81: Higher margins justify higher multiples; scales peer avg by margin ratio
B83: IMPLIED JAGEX EV AT DIFFERENT REGRESSION-DERIVED MULTIPLES
B84: Method | C84: Multiple | D84: Implied EV ($M, × $75M PF) | E84: Implied EV ($M, × $56.4M Rptd)
B85: Growth-based regression | C85: =C79 -> 9.7681481 | D85: =C79*75 -> 732.61111 | E85: =C79*56.4 -> 550.92356
B86: Tight peer average | C86: =C80 -> 7.55 | D86: =C80*75 -> 566.25 | E86: =C80*56.4 -> 425.82
B87: Margin-adjusted peer average | C87: =C81 -> 4.0622283 | D87: =C81*75 -> 304.66712 | E87: =C81*56.4 -> 229.10967
B88: Deal reference | C88: 15.1 | D88: 1136 | E88: 1136
B90: Reading: the regression provides a characteristics-based fair multiple (not a blunt median). If Jagex's growth is negative vs peer avg, the regression predicts a discount; if margin is above peer avg, the margin-adjustment predicts a premium. The two effects partially offset. Caveat: n=3 regression is a heuristic — useful for Q&A defense ("we considered growth and margin scaling") but not a rigorous econometric fit. With a larger comp set (say 8-10 tight peers) this would be a proper regression analysis.
B92: REGRESSION ON NORMALIZED JAGEX (PF EBITDA / margin basis)
B93: Jagex PF EBITDA margin vs tight peers
B94: Jagex normalized EBITDA margin (PF basis) | C94: =75/193.5 -> 0.3875969 | D94: Pro Forma $75M / TTM revenue $193.5M = 38.8% normalized
B95: Peer avg EBITDA margin | C95: =E73 -> 0.368
B96: Margin-adjusted mult (PF basis) | C96: =G73*(C94/C95) -> 7.9520559 | D96: Peer avg × (Jagex PF margin / peer margin); uses normalized — not trough
B97: Implied EV at PF margin-adjusted mult × $75M | C97: =C96*75 -> 596.4042 | D97: $M
B99: INTERPRETATION OF REGRESSION RESULTS
B100: All three peer-based methods (simple regression, tight peer avg, margin-adjusted) imply Jagex standalone trading value of ~$300-$733M. The deal at $1,136M represents a 55-280% premium — which IS the PE take-private control premium. This is NOT evidence the deal is overpriced; it IS evidence that CCA alone cannot justify the deal price. The PTA (transaction multiples) is the more relevant benchmark for a take-private. This is why the Football Field bridges CCA (low) to PTA (middle) to Deal (high) — the progression shows the control premium explicitly.
B102: Note on regression slope (C76 = -41.9): the negative slope reflects idiosyncratic 2026 market conditions — Frontier Developments (FDEV) currently trades at only 3.0x EV/EBITDA despite 15.8% revenue growth, while Paradox trades at 12.7x with flat growth. This is NOT a general market relationship; it is peer-set noise. With n=3, the regression is directional at best. A larger peer set (8-12 companies) would likely show the expected positive slope. The regression is retained in the model for Q&A defensibility ("we considered growth scaling") but the tight peer average (7.5x) and margin-adjusted multiple (PF basis, row 96) are more reliable.

Sheet PTA
B1: JAGEX — PRECEDENT TRANSACTION ANALYSIS (PTA)
B2: PitchBook M&A Comps | Downloaded 15-Apr-2026 | Gaming M&A deals 2021-2025
B3: Next Games excluded by user (EV/EBITDA -155x, distressed). 6 comps analyzed.
B5: PRECEDENT TRANSACTIONS
B6: Target | C6: Deal Date | D6: HQ | E6: Acquirer | F6: Deal Type | G6: EV/EBITDA | H6: EV/Rev | I6: Notes
B7: Sybo Games | C7: 24-Jun-2022 | D7: Copenhagen, DK | E7: Miniclip (Tencent) | F7: M&A | G7: 35.49 | H7: N/A | I7: Subway Surfers - hit mobile franchise; strategic premium
B8: Codemasters | C8: 18-Feb-2021 | D8: Southam, UK | E8: Electronic Arts (NAS:EA) | F8: M&A | G8: 29.8 | H8: 8.44 | I8: F1, DiRT racing franchise; strategic acquirer. EV/LTM Adj EBITDA at announcement (14-Dec-2020): £894.9M EV / £30.0M LTM Sep-2020 EBITDA = 29.83x. EV bridge: £945M equity − £50.1M net cash. LTM EBITDA = FY20 £18.2M + H1 FY21 £21.2M − H1 FY20 £9.4M (interim results filed 23-Nov-2020 under RNS 0926G). Cross-checked vs InvestGame.net published 29.8x. The 16.5x figure cited in some sources is the forward FY21 broker-consensus multiple, not trailing.
B9: Climax Studios | C9: 21-Apr-2021 | D9: Portsmouth, UK | E9: Keywords Studios (LON:KWS) | F9: M&A | G9: 13.56 | H9: 5.01 | I9: UK co-development studio
B10: astragon Entertainment | C10: 13-Jan-2022 | D10: Dusseldorf, DE | E10: Everplay Group (LON:EVPL) | F10: M&A | G10: 12.71 | H10: N/A | I10: Simulation games publisher (Construction Sim)
B11: Coffee Stain Gothenburg | C11: 19-Aug-2022 | D11: Gothenburg, SE | E11: Embracer Group (STO:EMBRAC B) | F11: M&A | G11: 2.4 | H11: 2.36 | I11: Satisfactory developer; internal restructuring
B12: Thunderful Group | C12: 30-Sep-2025 | D12: Gothenburg, SE | E12: Atari (PAR:ALATA) | F12: M&A | G12: 0.95 | H12: 0.24 | I12: Distressed Nordic publisher; non-normalized
B14: LEGEND: Light orange = potential outlier (reviewed below)
B16: SUMMARY STATISTICS
B17: Statistic | C17: EV/EBITDA (All 6) | D17: EV/EBITDA (Core 3) | F17: EV/Revenue (All 4) | G17: EV/Revenue (Core 2) | H17: Notes
B18: Mean | C18: 13.608333 | D18: 14.27 | F18: 4.0125 | G18: 6.725
B19: Median | C19: 13.135 | D19: 13.56 | F19: 3.685 | G19: 6.725
B20: 25th Percentile | C20: 4.9775 | D20: 13.135 | F20: 1.83 | G20: 5.8675
B21: 75th Percentile | C21: 15.795 | D21: 15.05 | F21: 5.8675 | G21: 7.5825
B22: Min | C22: 0.95 | D22: 12.71 | F22: 0.24 | G22: 5.01
B23: Max | C23: 35.49 | D23: 16.54 | F23: 8.44 | G23: 8.44
B25: Core set = 3 comps (Codemasters, Climax, astragon) excluding Sybo (35.49x hit-franchise premium) and Coffee Stain (2.40x internal restructuring)
B26: Core EV/Rev set = 2 comps (Codemasters 8.44x, Climax 5.01x) excluding Thunderful 0.24x (distressed) and Coffee Stain 2.36x (internal)
B28: IMPLIED JAGEX VALUATION
B29: Applied to Jagex Financials: | C29: Mult | D29: $M | E29: £M | I29: Basis
B30: Low (25th pct all) | C30: 4.9775 | D30: 373.3125 | E30: 295.64623 | I30: EV/EBITDA × PF $75M
B31: Median (all 6) | C31: 13.135 | D31: 985.125 | E31: 780.17344 | I31: EV/EBITDA × PF $75M
B32: Mean (all 6) | C32: 13.608333 | D32: 1020.625 | E32: 808.2878 | I32: EV/EBITDA × PF $75M
B33: High (75th pct all) | C33: 15.795 | D33: 1184.625 | E33: 938.16821 | I33: EV/EBITDA × PF $75M
B35: Median (core 3) | C35: 13.56 | D35: 1017 | E35: 805.41696 | I35: EV/EBITDA × PF $75M
B36: Mean (core 3) | C36: 14.27 | D36: 1070.25 | E36: 847.5885 | I36: EV/EBITDA × PF $75M
B38: Median (all 6) × Rptd EBITDA | C38: 13.135 | D38: 740.814 | E38: 586.69043 | I38: EV/EBITDA × Rptd $56.4M
B40: Median EV/Rev × Revenue | C40: 3.685 | D40: 695.728 | E40: 550.9844 | I40: EV/Rev × $188.8M
B41: Median EV/Rev (core) × Revenue | C41: 6.725 | D41: 1269.68 | E41: 1005.5278 | I41: EV/Rev × $188.8M
B43: Jagex Deal (reference) | C43: 15.1x | D43: 1136 | E43: 900 | I43: PitchBook: Deal/PF EBITDA 15.1x; Deal/Rptd 20.13x
B45: INTERPRETATION
B46: PTA implies Jagex valuation of $374M-$1,185M (£296M-£938M) at 25th-75th percentile of all 6 comps on pro forma EBITDA basis.
B47: Median-derived implied EV of $985M (£780M) is below deal price of $1,136M (£900M), implying Jagex commanded a ~15% premium to median PTA comp.
B48: Core set analysis (Codemasters, Climax, astragon) yields median 13.56x × $75M = $1,017M (£805M) — still below deal price but much closer to the actual multiple.
B49: Sybo Games (35.49x) represents strategic hit-franchise premium — Miniclip paid for the #1 mobile game globally (Subway Surfers). Not comparable to Jagex's MMORPG model.
B50: Coffee Stain Gothenburg (2.40x) and Thunderful (0.95x) represent internal restructurings and distressed deals. Also not comparable.
B51: Codemasters (16.54x EA acquisition, 2021) is the strongest single comp — UK gaming studio acquired by strategic buyer with live-service racing IP. This is MORE comparable to Jagex than the deal median suggests.
B52: Deal price of 20.13x reported EBITDA exceeds all PTA comps except Sybo, consistent with franchise quality premium for a 25-year live-service MMORPG.
B53: EV/Revenue analysis: Jagex deal at 6.02x sits between median EV/Rev of 3.68x (all 4) and max of 8.44x (Codemasters). Codemasters alone implies $1,595M (£1,263M) — above deal price.
B55: LIVE-SERVICE / TAKE-PRIVATE PRECEDENTS
B56: A focused set of directly comparable transactions: (i) the inferred seller precedent — Carlyle's January 2021 acquisition of Jagex from Macarthur Fortune at ~$530M / ~11.5x EV/EBITDA (Carlyle's actual 2021 price was never disclosed; $530M is the April 2020 confirmed price paid by Macarthur Fortune to Shanghai Hongtou / Shanghai Fukong, used here as a flat-hold proxy) — and (ii) the four landmark live-service take-privates from 2021-2024: Microsoft/Activision, Take-Two/Zynga, Sony/Bungie, EQT/Keywords. Codemasters/EA retained as the strongest UK direct comp. The broader 6-deal set above (rows 7-12) included small-cap deals that distort the multiple range; this expanded set provides cleaner benchmarks for the deal's 15.1x entry multiple.
B58: Target | C58: Deal Date | D58: Acquirer | E58: Type | F58: EV ($M) | G58: EV/EBITDA | H58: EV/Rev | I58: Notes / Source
B59: Jagex (Carlyle from Macarthur) ★ | C59: 25-Jan-2021 | D59: The Carlyle Group | E59: PE Platform | F59: 530 | G59: 11.5 | H59: 3.2 | I59: Most directly comparable: prior owner of Jagex; seller precedent. Carlyle Partners VII + Carlyle Europe Tech IV.
B60: Activision Blizzard | C60: 18-Jan-2022 | D60: Microsoft (NAS:MSFT) | E60: Take-Private | F60: 68700 | G60: 20.2 | H60: 7.6 | I60: Closed 13-Oct-2023; 45% premium; landmark live-service deal. EV/EBITDA on forecast FY21 Adj EBITDA at announcement (20.2x as cited by InvestGame); actual FY21 TTM was ~18.4-19.6x per SEC filings.
B61: Zynga | C61: 10-Jan-2022 | D61: Take-Two (NAS:TTWO) | E61: Take-Private (mixed cash/stock) | F61: 12700 | G61: 19.5 | H61: 4.5 | I61: Closed 23-May-2022; 64% premium; mobile live-service
B62: Keywords Studios | C62: 3-Jul-2024 | D62: EQT + CPP + Temasek | E62: Take-Private (UK) | F62: 2800 | G62: 15.9 | H62: 3.3 | I62: Closed 24-Oct-2024; 67% premium; UK gaming services take-private. Multiple stated verbatim in Rule 2.7 Recommended Final Cash Offer (3-Jul-2024): "...implies an enterprise value of approximately £2.2 billion and a multiple of approximately 15.9 times Keywords Studios' adjusted EBITDA for the 12-month period ended 31 December 2023 of £139 million." Cross-checks three ways: £2,200M÷£139M = 15.83x; €2,506M÷€158.3M = 15.83x; $2,800M÷~$176M = ~15.9x.
B63: Bungie | C63: 31-Jan-2022 | D63: Sony Interactive Entertainment | E63: Strategic (private→strategic) | F63: 3600 | H63: 4.1 | I63: Closed 15-Jul-2022; private→strategic; Destiny 2 live-service. Target was private; no public EBITDA disclosed — EV/EBITDA multiple not calculable from primary sources. EV/Revenue derived from estimated revenue ~$875M pre-deal.
B64: Codemasters | C64: 18-Feb-2021 | D64: Electronic Arts (NAS:EA) | E64: Take-Private (UK) | F64: 1200 | G64: 29.8 | H64: 8.44 | I64: UK live-service racing (F1/DiRT); strongest direct UK comp. EV/LTM Adj EBITDA at announcement: £894.9M EV / £30.0M LTM Sep-2020 = 29.83x. Verified against InvestGame.net (29.8x) and reconstructs from Codemasters H1 FY21 RNS + EA Rule 2.7 announcement (SEC EDGAR CIK 712515). The trailing basis is the standard M&A multiple — forward FY21 was ~16.5x and stale FY20 was ~50x; 29.8x is the period-correct LTM figure.
B66: EXPANDED-SET SUMMARY STATISTICS
B67: Statistic | C67: EV/EBITDA | D67: EV/Revenue
B68: Mean (incl. seller precedent) | C68: =AVERAGE(G59:G64) -> 19.38 | D68: =AVERAGE(H59:H64) -> 5.19
B69: Median (incl. seller precedent) | C69: =MEDIAN(G59:G64) -> 19.5 | D69: =MEDIAN(H59:H64) -> 4.3
B70: Median ex-seller (live-service take-privates only) | C70: =MEDIAN(G60:G64) -> 19.85 | D70: =MEDIAN(H60:H64) -> 4.5
B71: 25th Percentile | C71: =PERCENTILE(G59:G64,0.25) -> 15.9 | D71: =PERCENTILE(H59:H64,0.25) -> 3.5
B72: 75th Percentile | C72: =PERCENTILE(G59:G64,0.75) -> 20.2 | D72: =PERCENTILE(H59:H64,0.75) -> 6.825
B74: IMPLIED JAGEX EV — EXPANDED-SET MEDIAN MULTIPLES
B75: Median EV/EBITDA × $75M PF EBITDA | C75: =C69*75 -> 1462.5 | D75: $M
B76: Median EV/EBITDA × $56.4M Reported EBITDA | C76: =C69*56.4 -> 1099.8 | D76: $M
B77: Median EV/Revenue × $188.8M Revenue | C77: =D69*188.8 -> 811.84 | D77: $M
B78: Deal Reference | C78: 1136 | D78: $M
B80: EXPANDED-SET INTERPRETATION
B81: The expanded set (Carlyle/Jagex 2021 + 4 live-service take-privates + Codemasters) yields a tighter and more directly comparable EV/EBITDA range than the broader 6-deal set above. The seller precedent (Carlyle/Jagex Jan 2021 at ~11.5x) sits well BELOW the live-service take-private median (~19-20x EV/EBITDA), reflecting the difference between (i) a sponsor secondary at trough EBITDA in a private-credit-tight 2021 environment, and (ii) strategic / take-private premiums in a 2022-2024 live-service consolidation wave. The CVC/Haveli 2024 deal at ~15x PF EBITDA sits between these poles, reflecting a sponsor secondary (lower than strategic premium) of a higher-quality asset (multiple expansion vs Carlyle 2021).

Sheet DCF
B1: JAGEX — DISCOUNTED CASH FLOW ANALYSIS
B2: Paper DCF with PitchBook-sourced base year | (£ in millions)
B5: KEY ASSUMPTIONS (yellow = editable)
B6: Base Revenue FY2023 (£M) | C6: 149 | D6: PitchBook TTM $188.8M ÷ 1.27
B7: Base Reported EBITDA FY2023 (£M) | C7: 44.4 | D7: PitchBook TTM $56.4M ÷ 1.27
B8: Base Pro Forma EBITDA FY2023 (£M) | C8: 59.4 | D8: PitchBook $75M ÷ 1.263
B9: Revenue Growth Y1-Y2 | C9: 0.08 | D9: Paper: moderate (PitchBook shows 10.5% trailing)
B10: Revenue Growth Y3-Y5 | C10: 0.05 | D10: Paper: mature growth rate
B11: EBITDA Margin (use pro forma basis) | C11: 0.4 | D11: Paper: 39.7% pro forma FY23 ($75M/$188.8M), assume slight expansion
B12: D&A % of Revenue | C12: 0.048 | D12: Derived: PitchBook D&A ≈ £7.1M / £149M = 4.8%
B13: Tax Rate | C13: 0.25 | D13: UK Corporation Tax (standard rate)
B14: CapEx % of Revenue | C14: 0.045 | D14: Derived: intangible investment ~$8.7M/yr (FY23 growth) / $188.8M rev = 4.6%
B15: ΔNWC % of ΔRevenue | C15: 0.05 | D15: Paper: subscription model = modest NWC needs
B16: WACC | C16: 0.1 | D16: Paper: private company, gaming risk premium
B17: Terminal Growth Rate | C17: 0.025 | D17: Paper: long-lived franchise, 25yr track record
B19: PROJECTED UNLEVERED FREE CASH FLOW
C20: FY2024E | D20: FY2025E | E20: FY2026E | F20: FY2027E | G20: FY2028E
B21: Revenue | C21: =C6*(1+C9) -> 160.92 | D21: =C21*(1+C9) -> 173.7936 | E21: =D21*(1+C10) -> 182.48328 | F21: =E21*(1+C10) -> 191.60744 | G21: =F21*(1+C10) -> 201.18782
B22: EBITDA | C22: =C21*C11 -> 64.368 | D22: =D21*C11 -> 69.51744 | E22: =E21*C11 -> 72.993312 | F22: =F21*C11 -> 76.642978 | G22: =G21*C11 -> 80.475126
B23: (-) D&A | C23: =-C21*C12 -> -7.72416 | D23: =-D21*C12 -> -8.3420928 | E23: =-E21*C12 -> -8.7591974 | F23: =-F21*C12 -> -9.1971573 | G23: =-G21*C12 -> -9.6570152
B24: EBIT | C24: =C22+C23 -> 56.64384 | D24: =D22+D23 -> 61.175347 | E24: =E22+E23 -> 64.234115 | F24: =F22+F23 -> 67.44582 | G24: =G22+G23 -> 70.818111
B25: (-) Taxes on EBIT | C25: =-C24*C13 -> -14.16096 | D25: =-D24*C13 -> -15.293837 | E25: =-E24*C13 -> -16.058529 | F25: =-F24*C13 -> -16.861455 | G25: =-G24*C13 -> -17.704528
B26: NOPAT | C26: =C24+C25 -> 42.48288 | D26: =D24+D25 -> 45.88151 | E26: =E24+E25 -> 48.175586 | F26: =F24+F25 -> 50.584365 | G26: =G24+G25 -> 53.113583
B27: (+) D&A Add-back | C27: =-C23 -> 7.72416 | D27: =-D23 -> 8.3420928 | E27: =-E23 -> 8.7591974 | F27: =-F23 -> 9.1971573 | G27: =-G23 -> 9.6570152
B28: (-) CapEx | C28: =-C21*C14 -> -7.2414 | D28: =-D21*C14 -> -7.820712 | E28: =-E21*C14 -> -8.2117476 | F28: =-F21*C14 -> -8.622335 | G28: =-G21*C14 -> -9.0534517
B29: (-) Chg in NWC | C29: =-(C21-C6)*C15 -> -0.596 | D29: =-(D21-C21)*C15 -> -0.64368 | E29: =-(E21-D21)*C15 -> -0.434484 | F29: =-(F21-E21)*C15 -> -0.4562082 | G29: =-(G21-F21)*C15 -> -0.47901861
B30: Unlevered Free Cash Flow | C30: =C26+C27+C28+C29 -> 42.36964 | D30: =D26+D27+D28+D29 -> 45.759211 | E30: =E26+E27+E28+E29 -> 48.288552 | F30: =F26+F27+F28+F29 -> 50.702979 | G30: =G26+G27+G28+G29 -> 53.238128
B31: Discount Factor | C31: =1/(1+C16)^1 -> 0.90909091 | D31: =1/(1+C16)^2 -> 0.82644628 | E31: =1/(1+C16)^3 -> 0.7513148 | F31: =1/(1+C16)^4 -> 0.68301346 | G31: =1/(1+C16)^5 -> 0.62092132
B32: PV of UFCF | C32: =C30*C31 -> 38.517855 | D32: =D30*D31 -> 37.81753 | E32: =E30*E31 -> 36.279904 | F32: =F30*F31 -> 34.630817 | G32: =G30*G31 -> 33.056689
B34: TERMINAL VALUE & ENTERPRISE VALUE
B35: Terminal Value (Gordon Growth) | C35: =G30*(1+C17)/(C16-C17) -> 727.58775 | D35: UFCF_Y5 × (1+g) / (WACC-g)
B36: PV of Terminal Value | C36: =C35*G31 -> 451.77475
B37: Sum of PV of UFCFs | C37: =SUM(C32:G32) -> 180.30279
B38: Implied Enterprise Value (£M) | C38: =C36+C37 -> 632.07754
B39: TV as % of EV | C39: =C36/C38 -> 0.71474577
B40: Implied EV / Pro Forma EBITDA | C40: =C38/C8 -> 10.641036
B41: Deal Price for Reference (£M) | C41: 900 | D41: £900M ($1,136M / 1.2627)
B43: SENSITIVITY: IMPLIED EV (£M) — WACC vs Terminal Growth Rate
B44: WACC \ TGR | C44: 0.015 | D44: 0.02 | E44: 0.025 | F44: 0.03 | G44: 0.035
B45: 0.08 | C45: =C30/(1+$B45)^1+D30/(1+$B45)^2+E30/(1+$B45)^3+F30/(1+$B45)^4+G30/(1+$B45)^5+G30*(1+C$44)/($B45-C$44)/(1+$B45)^5 -> 756.08833 | D45: =C30/(1+$B45)^1+D30/(1+$B45)^2+E30/(1+$B45)^3+F30/(1+$B45)^4+G30/(1+$B45)^5+G30*(1+D$44)/($B45-D$44)/(1+$B45)^5 -> 806.25707 | E45: =C30/(1+$B45)^1+D30/(1+$B45)^2+E30/(1+$B45)^3+F30/(1+$B45)^4+G30/(1+$B45)^5+G30*(1+E$44)/($B45-E$44)/(1+$B45)^5 -> 865.54739 | F45: =C30/(1+$B45)^1+D30/(1+$B45)^2+E30/(1+$B45)^3+F30/(1+$B45)^4+G30/(1+$B45)^5+G30*(1+F$44)/($B45-F$44)/(1+$B45)^5 -> 936.69578 | G45: =C30/(1+$B45)^1+D30/(1+$B45)^2+E30/(1+$B45)^3+F30/(1+$B45)^4+G30/(1+$B45)^5+G30*(1+G$44)/($B45-G$44)/(1+$B45)^5 -> 1023.6549
B46: 0.09 | C46: =C30/(1+$B46)^1+D30/(1+$B46)^2+E30/(1+$B46)^3+F30/(1+$B46)^4+G30/(1+$B46)^5+G30*(1+C$44)/($B46-C$44)/(1+$B46)^5 -> 653.4625 | D46: =C30/(1+$B46)^1+D30/(1+$B46)^2+E30/(1+$B46)^3+F30/(1+$B46)^4+G30/(1+$B46)^5+G30*(1+D$44)/($B46-D$44)/(1+$B46)^5 -> 689.38177 | E46: =C30/(1+$B46)^1+D30/(1+$B46)^2+E30/(1+$B46)^3+F30/(1+$B46)^4+G30/(1+$B46)^5+G30*(1+E$44)/($B46-E$44)/(1+$B46)^5 -> 730.82708 | F46: =C30/(1+$B46)^1+D30/(1+$B46)^2+E30/(1+$B46)^3+F30/(1+$B46)^4+G30/(1+$B46)^5+G30*(1+F$44)/($B46-F$44)/(1+$B46)^5 -> 779.17994 | G46: =C30/(1+$B46)^1+D30/(1+$B46)^2+E30/(1+$B46)^3+F30/(1+$B46)^4+G30/(1+$B46)^5+G30*(1+G$44)/($B46-G$44)/(1+$B46)^5 -> 836.32423
B47: 0.1 | C47: =C30/(1+$B47)^1+D30/(1+$B47)^2+E30/(1+$B47)^3+F30/(1+$B47)^4+G30/(1+$B47)^5+G30*(1+C$44)/($B47-C$44)/(1+$B47)^5 -> 575.03855 | D47: =C30/(1+$B47)^1+D30/(1+$B47)^2+E30/(1+$B47)^3+F30/(1+$B47)^4+G30/(1+$B47)^5+G30*(1+D$44)/($B47-D$44)/(1+$B47)^5 -> 601.77558 | E47: =C30/(1+$B47)^1+D30/(1+$B47)^2+E30/(1+$B47)^3+F30/(1+$B47)^4+G30/(1+$B47)^5+G30*(1+E$44)/($B47-E$44)/(1+$B47)^5 -> 632.07754 | F47: =C30/(1+$B47)^1+D30/(1+$B47)^2+E30/(1+$B47)^3+F30/(1+$B47)^4+G30/(1+$B47)^5+G30*(1+F$44)/($B47-F$44)/(1+$B47)^5 -> 666.70836 | G47: =C30/(1+$B47)^1+D30/(1+$B47)^2+E30/(1+$B47)^3+F30/(1+$B47)^4+G30/(1+$B47)^5+G30*(1+G$44)/($B47-G$44)/(1+$B47)^5 -> 706.667
B48: 0.11 | C48: =C30/(1+$B48)^1+D30/(1+$B48)^2+E30/(1+$B48)^3+F30/(1+$B48)^4+G30/(1+$B48)^5+G30*(1+C$44)/($B48-C$44)/(1+$B48)^5 -> 513.17157 | D48: =C30/(1+$B48)^1+D30/(1+$B48)^2+E30/(1+$B48)^3+F30/(1+$B48)^4+G30/(1+$B48)^5+G30*(1+D$44)/($B48-D$44)/(1+$B48)^5 -> 533.68011 | E48: =C30/(1+$B48)^1+D30/(1+$B48)^2+E30/(1+$B48)^3+F30/(1+$B48)^4+G30/(1+$B48)^5+G30*(1+E$44)/($B48-E$44)/(1+$B48)^5 -> 556.60142 | F48: =C30/(1+$B48)^1+D30/(1+$B48)^2+E30/(1+$B48)^3+F30/(1+$B48)^4+G30/(1+$B48)^5+G30*(1+F$44)/($B48-F$44)/(1+$B48)^5 -> 582.3879 | G48: =C30/(1+$B48)^1+D30/(1+$B48)^2+E30/(1+$B48)^3+F30/(1+$B48)^4+G30/(1+$B48)^5+G30*(1+G$44)/($B48-G$44)/(1+$B48)^5 -> 611.61257
B49: 0.12 | C49: =C30/(1+$B49)^1+D30/(1+$B49)^2+E30/(1+$B49)^3+F30/(1+$B49)^4+G30/(1+$B49)^5+G30*(1+C$44)/($B49-C$44)/(1+$B49)^5 -> 463.1291 | D49: =C30/(1+$B49)^1+D30/(1+$B49)^2+E30/(1+$B49)^3+F30/(1+$B49)^4+G30/(1+$B49)^5+G30*(1+D$44)/($B49-D$44)/(1+$B49)^5 -> 479.24043 | E49: =C30/(1+$B49)^1+D30/(1+$B49)^2+E30/(1+$B49)^3+F30/(1+$B49)^4+G30/(1+$B49)^5+G30*(1+E$44)/($B49-E$44)/(1+$B49)^5 -> 497.04769 | F49: =C30/(1+$B49)^1+D30/(1+$B49)^2+E30/(1+$B49)^3+F30/(1+$B49)^4+G30/(1+$B49)^5+G30*(1+F$44)/($B49-F$44)/(1+$B49)^5 -> 516.83353 | G49: =C30/(1+$B49)^1+D30/(1+$B49)^2+E30/(1+$B49)^3+F30/(1+$B49)^4+G30/(1+$B49)^5+G30*(1+G$44)/($B49-G$44)/(1+$B49)^5 -> 538.94712
B52: WACC BUILD (CAPM)
B53: HOW WE BUILT THE WACC
B54: The WACC is the discount rate we apply to Jagex's projected cash flows in the DCF. It represents the blended return that capital providers — equity investors and lenders — would require to fund a business with this risk profile and capital structure. We construct it from first principles using the Capital Asset Pricing Model for the equity component and observable market spreads for debt, rather than picking a round number. Every input below is sourced to a primary dataset that a reader can independently verify.
B55: Risk-free rate — 4.32% | C55: The yield on the UK 10-year gilt in late May 2024, which is when the deal closed (14 May 2024). We use the 10-year tenor because it broadly matches the long-dated horizon of a going-concern enterprise valuation — using a short-dated rate (e.g. 1-year) would understate duration risk, while using a 30-year would overstate liquidity premium. We use UK gilts rather than US Treasuries because Jagex is a UK-domiciled company modeled in GBP; mixing currencies on the risk-free rate would introduce an unhedged FX assumption. Source: Bank of England yield curve archive.
B56: Equity risk premium — 5.01% | C56: The premium investors demand to hold UK equities over the risk-free rate, taken from Damodaran's January 2026 country risk premium dataset. It is built as 4.23% (the implied premium on mature developed markets, derived from S&P 500 expected returns net of US Treasury yields) plus 0.78% (the UK-specific country risk premium reflecting Moody's Aa3 sovereign rating). We use the implied method rather than historical realized returns because implied premia are forward-looking and self-correcting to current market prices, while realized premia are backward-looking and sensitive to the chosen lookback window.
B57: Beta — unlevered 1.02, relevered 1.21 | C57: Beta measures systematic risk — how much the asset moves with the broader market. We start from Damodaran's January 2026 sector data for "Software (Entertainment)," which covers 77 listed game publishers and is the cleanest available proxy for Jagex's business model. The cash-corrected unlevered beta for that sector is 1.02. We then relever this beta to Jagex's target capital structure using the Hamada equation: βL = βU × [1 + (1−t) × D/E]. With a target debt-to-capital of 20% (D/E ≈ 0.25) and a UK statutory tax rate of 25%, the relevering multiplier is 1.1875, producing a levered beta of 1.21. We chose Damodaran's sector beta over a peer-average computed from individual gaming companies because the public peer set is dominated by small-cap UK and Swedish issuers (Frontier Developments, Paradox Interactive, Everplay) whose individual betas suffer from severe measurement noise — Frontier's 5-year monthly beta against the FTSE 100 prints as negative, which is implausible for a discretionary consumer-tech business and reflects liquidity-driven mispricing rather than true systematic risk.
B58: Cost of equity — 10.4% | C58: Combining the components via CAPM: Re = Rf + βL × ERP = 4.32% + 1.21 × 5.01% = 10.4%. This is the return equity holders would demand to fund the deal at the assumed leverage profile. It sits comfortably within the 8-13% range typical for mid-cap UK technology and gaming names.
B59: After-tax cost of debt — 8.4% | C59: The all-in interest rate on Jagex's new senior debt, less the value of the interest tax shield. Pre-tax: SONIA at deal close was 5.20% (Bank of England IUDSOIA series, 14 May 2024); the credit margin of 600 basis points reflects PitchBook reporting on the Apollo/Oaktree/Permira unitranche facility, consistent with UK direct-lender pricing for similar 2024 vintage take-privates which ranged ~SONIA+550-700bps. The all-in pre-tax cost of 11.20% is then reduced by the 25% UK corporate tax rate to give 8.40% after-tax — debt service is deductible against UK profits, so the effective economic cost to the business is lower than the headline coupon.
B60: Capital structure — 80% equity / 20% debt | C60: The target long-run mix used to weight the two costs. We use a normalized capital structure rather than the LBO's entry leverage (which is materially higher at deal close) because the DCF values the business as a going concern beyond the immediate post-LBO period. Sponsors typically delever over the hold by paying down term debt with free cash flow; by Year 5, Jagex's leverage profile should normalize toward the sector average. A 20% debt weighting reflects the lighter long-run leverage typical of cash-generative live-service publishers.
B61: Resulting WACC — 10.0% | C61: WACC = (E/V × Re) + (D/V × Kd_after_tax) = (80% × 10.4%) + (20% × 8.4%) = 10.0%. The result is sensitive to capital-structure assumptions: at 30% target debt the WACC compresses to roughly 9.8%, and at 10% it expands to roughly 10.2%. The DCF sensitivity table at B43:G49 flexes WACC across the 8-12% range to capture this parameter uncertainty, with the base case anchored at 10.0%.
B63: CAPM BUILD (DETAIL)
B67: Cost of Equity (CAPM)
B68: Risk-free rate (UK 10yr gilt, May 2024) | C68: 0.0432 | D68: Late-May 2024 UK 10yr gilt yield 4.32% (BoE yield curve archive); May average sits in 4.30-4.35% range.
B69: Equity Risk Premium (UK total) | C69: 0.0501 | D69: Damodaran Jan-2026: 4.23% mature-market base + 0.78% UK country risk premium = 5.01% total ERP.
B70: Unlevered β (Software Entertainment, cash-corrected) | C70: 1.02 | D70: Damodaran Jan-2026 "Software (Entertainment)" sector: n=77 firms, βU=1.01, cash-corrected βU=1.02. Pure-play game publisher bucket — directly comparable to Jagex.
B71: Relevering multiplier [1+(1-t)×D/E] | C71: =1+(1-C13)*(C76/(1-C76)) -> 1.1875 | D71: Hamada relever: D/E from D/Cap = 0.25 (D/Cap=0.20 / E/Cap=0.80); tax rate 25%; multiplier = 1+0.75×0.25 = 1.1875.
B72: Levered β (relevered to LBO target capital structure) | C72: =C70*C71 -> 1.21125 | D72: Software (Entertainment) βU 1.02 × relevering multiplier 1.1875 = 1.21. Peer average levered β (Paradox/Frontier/Everplay/TTWO/EA) ~0.83 is downward-biased by small-cap measurement noise (Frontier produces β=-0.10 vs FTSE 100 — implausible) and net-cash balance sheets; used as sanity check only.
B73: Cost of Equity (Re) | C73: =C68+C72*C69 -> 0.10388363 | D73: CAPM: Rf + βL × ERP = 4.32% + 1.21 × 5.01% = 10.4%
B74: Pre-tax Cost of Debt (Rd) | C74: 0.112 | D74: SONIA 5.20% (May 2024) + 600bps spread (illustrative)
B75: After-tax Cost of Debt | C75: =C74*(1-C13) -> 0.084 | D75: Rd × (1 - tax rate of 25%)
B76: Target Debt / Capital | C76: 0.2
B77: Implied WACC | C77: =(1-C76)*C73+C76*C75 -> 0.0999069 | D77: WACC = E/V × Re + D/V × Kd(1-t)
B78: Note: model uses 10.0% WACC at C16 (paper assumption). The CAPM-derived WACC of 10.0% above reconciles exactly within rounding (Re 10.4% × 80% + Kd 8.4% × 20% = 10.0%). The sensitivity table at B43:G49 covers the WACC 8-12% range to capture parameter uncertainty.
B80: TERMINAL GROWTH RATE RATIONALE
B81: TGR 2.5% (C17) bracketed by: (i) UK long-run real GDP growth ~1.5-2.0%; (ii) UK long-run inflation target ~2.0%; (iii) live-service gaming nominal growth premium ~50-100bps over GDP+inflation due to "forever game" recurring revenue model and 67% PC player-hours on titles >6 years old (Newzoo 2024). A 2.5% nominal terminal growth = real GDP + inflation - small premium for non-extrapolation. Sensitivity tested 1.5%-3.5%.
B84: FX CONVENTION
B85: FX rate: 1.2627 GBP/USD (May 2024 average per X-Rates). Close-day spot was 1.2598 (14 May 2024). Difference is <0.3% — immaterial in all model outputs.

Sheet LBO Model
B1: JAGEX — LBO RETURNS ANALYSIS (PitchBook Actual)
B2: CVC/Haveli from Carlyle | Closed 14-May-2024 | (£M) | FX: 1.263
B4: SOURCES & USES (PitchBook Actual)
B5: Sources | C5: Amount (£M) | D5: Amount ($M) | E5: x EBITDA | F5: % Total
B6: Term Loan (7yr, mat 13-May-2031) | C6: 103.4 | D6: 130.63 | E6: =C6/$C$20 -> 1.7407407 | F6: =C6/C10 -> 0.11488889 | J6: PitchBook Debt Summary: $130.63M TL, SONIA+600, 7yr
B7: Revolving Credit Facility | C7: 28.6 | D7: 36.17 | E7: =C7/$C$20 -> 0.48148148 | F7: =C7/C10 -> 0.031777778 | J7: PitchBook Debt Summary: $36.17M RCF, SONIA+600
B8: Total New Debt | C8: =SUM(C6:C7) -> 132 | D8: =SUM(D6:D7) -> 166.8 | E8: =C8/$C$20 -> 2.2222222 | F8: =C8/C10 -> 0.14666667 | J8: PitchBook: Total New Debt $164.15M
B9: Sponsor Equity (CVC VIII + Haveli) | C9: =C10-C8 -> 768 | D9: =D10-D8 -> 969.2 | E9: =C9/$C$20 -> 12.929293 | F9: =C9/C10 -> 0.85333333 | J9: Residual: Deal Amount − Total Debt
B10: Total Sources = Deal Amount | C10: 900 | D10: 1136 | E10: =C10/59.4 -> 15.151515 | F10: =C10/C10 -> 1 | J10: PitchBook: $1,136,109K; at 1.2627 = £900M (press: £910M)
B12: LENDERS AT ISSUANCE (PitchBook)
B13: Apollo Global Mgmt (Debt Solutions BDC) | C13: $72.02M TL + $19.94M RCF = $91.96M | J13: PitchBook Lenders #4-5
B14: Oaktree Capital Mgmt (Strategic Credit BDC) | C14: $56.53M TL + $15.66M RCF = $72.19M | J14: PitchBook Lenders #6-7
B15: Permira | C15: RCF + TL (amounts not disclosed) | J15: PitchBook Lenders #3, #8
B16: Oaktree Capital Mgmt (Mezzanine) | C16: TL + RCF (amounts not disclosed) | J16: PitchBook Lenders #1-2
B18: OPERATING ASSUMPTIONS (yellow = editable)
B19: Entry EV (£M) | C19: 903 | D19: PitchBook: Implied EV $1.09B ÷ 1.263 → £863M; Deal Amount £903M used
B20: Pro Forma EBITDA at Entry (£M) | C20: 59.4 | D20: PitchBook: $75M ÷ 1.263
B21: Entry Multiple (Deal/PF EBITDA) | C21: =C19/C20 -> 15.20202 | D21: Calculated
B22: Reported EBITDA at Entry (£M) | C22: 44.4 | D22: PitchBook TTM: $56.4M ÷ 1.27
B23: Entry Multiple (Deal/Rptd EBITDA) | C23: =C19/C22 -> 20.337838 | D23: Calculated; PitchBook shows 20.13x
B24: Base Revenue (£M) | C24: 149 | D24: PitchBook TTM: $188.8M ÷ 1.27
B25: Revenue Growth Y1-Y2 | C25: 0.08 | D25: Paper: moderate (trailing 10.5%)
B26: Revenue Growth Y3-Y5 | C26: 0.05 | D26: Paper: mature
B27: EBITDA Margin (Pro Forma basis) | C27: 0.4 | D27: Paper: 39.7% PF FY23 + slight expansion
B28: D&A % Revenue | C28: 0.048 | D28: Derived: PitchBook D&A £7.1M / £149M
B29: Tax Rate | C29: 0.25 | D29: UK Corp Tax
B30: CapEx % Revenue | C30: 0.045 | D30: Derived: intangible investment proxy; matches DCF assumption
B31: ΔNWC % ΔRevenue | C31: 0.05 | D31: Paper
B32: SONIA Rate (at close) | C32: 0.052 | D32: Bank of England: 5.20% (May 7 2024 onward)
B33: Spread (TL & RCF) | C33: 0.06 | D33: PitchBook: SONIA + 600bps
B34: All-in Interest Rate | C34: =C32+C33 -> 0.112 | D34: Calculated: SONIA + Spread
B35: Mandatory Amort (% orig TL) | C35: 0.01 | D35: Paper: 1% p.a. standard
B36: Cash Sweep % | C36: 0.5 | D36: Paper: 50% excess CF
B38: OPERATING MODEL
C39: Entry | D39: Year 1 | E39: Year 2 | F39: Year 3 | G39: Year 4 | H39: Year 5
B40: Revenue | C40: =C24 -> 149 | D40: =C40*(1+C25) -> 160.92 | E40: =D40*(1+C25) -> 173.7936 | F40: =E40*(1+C26) -> 182.48328 | G40: =F40*(1+C26) -> 191.60744 | H40: =G40*(1+C26) -> 201.18782
B41: EBITDA | C41: =C20 -> 59.4 | D41: =D40*C27 -> 64.368 | E41: =E40*C27 -> 69.51744 | F41: =F40*C27 -> 72.993312 | G41: =G40*C27 -> 76.642978 | H41: =H40*C27 -> 80.475126
B42: (-) D&A | C42: =C40*C28 -> 7.152 | D42: =D40*C28 -> 7.72416 | E42: =E40*C28 -> 8.3420928 | F42: =F40*C28 -> 8.7591974 | G42: =G40*C28 -> 9.1971573 | H42: =H40*C28 -> 9.6570152
B43: EBIT | C43: =C41-C42 -> 52.248 | D43: =D41-D42 -> 56.64384 | E43: =E41-E42 -> 61.175347 | F43: =F41-F42 -> 64.234115 | G43: =G41-G42 -> 67.44582 | H43: =H41-H42 -> 70.818111
B44: (-) Interest: Term Loan | C44: =C56*C34 -> 11.5808 | D44: =D56*C34 -> 11.5808 | E44: =E56*C34 -> 9.6944938 | F44: =F56*C34 -> 7.5391467 | G44: =G56*C34 -> 5.1516319 | H44: =H56*C34 -> 2.5286336
B45: Total Interest Expense | C45: =C44 -> 11.5808 | D45: =D44 -> 11.5808 | E45: =E44 -> 9.6944938 | F45: =F44 -> 7.5391467 | G45: =G44 -> 5.1516319 | H45: =H44 -> 2.5286336
B46: EBT | C46: =C43-C45 -> 40.6672 | D46: =D43-D45 -> 45.06304 | E46: =E43-E45 -> 51.480853 | F46: =F43-F45 -> 56.694968 | G46: =G43-G45 -> 62.294188 | H46: =H43-H45 -> 68.289478
B47: (-) Taxes | C47: =MAX(0,C46*C29) -> 10.1668 | D47: =MAX(0,D46*C29) -> 11.26576 | E47: =MAX(0,E46*C29) -> 12.870213 | F47: =MAX(0,F46*C29) -> 14.173742 | G47: =MAX(0,G46*C29) -> 15.573547 | H47: =MAX(0,H46*C29) -> 17.072369
B48: Net Income | C48: =C46-C47 -> 30.5004 | D48: =D46-D47 -> 33.79728 | E48: =E46-E47 -> 38.61064 | F48: =F46-F47 -> 42.521226 | G48: =G46-G47 -> 46.720641 | H48: =H46-H47 -> 51.217108
B49: (+) D&A | C49: =C42 -> 7.152 | D49: =D42 -> 7.72416 | E49: =E42 -> 8.3420928 | F49: =F42 -> 8.7591974 | G49: =G42 -> 9.1971573 | H49: =H42 -> 9.6570152
B50: (-) CapEx | C50: =C40*C30 -> 6.705 | D50: =D40*C30 -> 7.2414 | E50: =E40*C30 -> 7.820712 | F50: =F40*C30 -> 8.2117476 | G50: =G40*C30 -> 8.622335 | H50: =H40*C30 -> 9.0534517
B51: (-) Chg in NWC | C51: 0 | D51: =(D40-C40)*C31 -> 0.596 | E51: =(E40-D40)*C31 -> 0.64368 | F51: =(F40-E40)*C31 -> 0.434484 | G51: =(G40-F40)*C31 -> 0.4562082 | H51: =(H40-G40)*C31 -> 0.47901861
B52: Levered Free Cash Flow | C52: =C48+C49-C50-C51 -> 30.9474 | D52: =D48+D49-D50-D51 -> 33.68404 | E52: =E48+E49-E50-E51 -> 38.488341 | F52: =F48+F49-F50-F51 -> 42.634192 | G52: =G48+G49-G50-G51 -> 46.839255 | H52: =H48+H49-H50-H51 -> 51.341653
B54: DEBT SCHEDULE (PitchBook Actual Structure)
C55: Entry | D55: Year 1 | E55: Year 2 | F55: Year 3 | G55: Year 4 | H55: Year 5
B56: Term Loan — Beginning | C56: 103.4 | D56: =C59 -> 103.4 | E56: =D59 -> 86.55798 | F56: =E59 -> 67.31381 | G56: =F59 -> 45.996714 | H56: =G59 -> 22.577086
B57: (-) Mandatory Amortization | C57: 0 | D57: =C56*C35 -> 1.034 | E57: =C56*C35 -> 1.034 | F57: =C56*C35 -> 1.034 | G57: =C56*C35 -> 1.034 | H57: =C56*C35 -> 1.034
B58: (-) Cash Sweep Paydown | C58: 0 | D58: =MIN(MAX(0,D52*C36-D57),D56-D57) -> 15.80802 | E58: =MIN(MAX(0,E52*C36-E57),E56-E57) -> 18.21017 | F58: =MIN(MAX(0,F52*C36-F57),F56-F57) -> 20.283096 | G58: =MIN(MAX(0,G52*C36-G57),G56-G57) -> 22.385628 | H58: =MIN(MAX(0,H52*C36-H57),H56-H57) -> 21.543086
B59: Term Loan — Ending | C59: =C56 -> 103.4 | D59: =D56-D57-D58 -> 86.55798 | E59: =E56-E57-E58 -> 67.31381 | F59: =F56-F57-F58 -> 45.996714 | G59: =G56-G57-G58 -> 22.577086 | H59: =H56-H57-H58 -> 0
B61: Total Debt Outstanding | C61: =C59 -> 103.4 | D61: =D59 -> 86.55798 | E61: =E59 -> 67.31381 | F61: =F59 -> 45.996714 | G61: =G59 -> 22.577086 | H61: =H59 -> 0
B62: Leverage (Debt / Pro Forma EBITDA) | C62: =C61/C41 -> 1.7407407 | D62: =D61/D41 -> 1.3447362 | E62: =E61/E41 -> 0.96830104 | F62: =F61/F41 -> 0.6301497 | G62: =G61/G41 -> 0.29457475 | H62: =H61/H41 -> 0
B63: Interest Coverage (EBITDA / Interest) | C63: =IF(C45=0,"-",C41/C45) -> 5.1291793 | D63: =IF(D45=0,"-",D41/D45) -> 5.5581652 | E63: =IF(E45=0,"-",E41/E45) -> 7.1708169 | F63: =IF(F45=0,"-",F41/F45) -> 9.6819063 | G63: =IF(G45=0,"-",G41/G45) -> 14.877417 | H63: =IF(H45=0,"-",H41/H45) -> 31.825538
B65: RETURNS ANALYSIS — MOIC & IRR
B66: Exit EV/EBITDA | C66: Year 3 Exit | E66: Year 4 Exit | G66: Year 5 Exit
C67: MOIC | D67: IRR | E67: MOIC | F67: IRR | G67: MOIC | H67: IRR
B68: 12 | C68: =($B68*F41-F61)/C9 -> 1.0806289 | D68: =IF(C68<=0,"N/A",C68^(1/3)-1) -> 0.026184693 | E68: =($B68*G41-G61)/C9 -> 1.1681493 | F68: =IF(E68<=0,"N/A",E68^(1/4)-1) -> 0.039619905 | G68: =($B68*H41-H61)/C9 -> 1.2574239 | H68: =IF(G68<=0,"N/A",G68^(1/5)-1) -> 0.04687864
B69: 13 | C69: =($B69*F41-F61)/C9 -> 1.1756723 | D69: =IF(C69<=0,"N/A",C69^(1/3)-1) -> 0.055428372 | E69: =($B69*G41-G61)/C9 -> 1.2679448 | F69: =IF(E69<=0,"N/A",E69^(1/4)-1) -> 0.061145871 | G69: =($B69*H41-H61)/C9 -> 1.3622092 | H69: =IF(G69<=0,"N/A",G69^(1/5)-1) -> 0.063772503
B70: 14 | C70: =($B70*F41-F61)/C9 -> 1.2707157 | D70: =IF(C70<=0,"N/A",C70^(1/3)-1) -> 0.08313552 | E70: =($B70*G41-G61)/C9 -> 1.3677404 | F70: =IF(E70<=0,"N/A",E70^(1/4)-1) -> 0.081436232 | G70: =($B70*H41-H61)/C9 -> 1.4669945 | H70: =IF(G70<=0,"N/A",G70^(1/5)-1) -> 0.079656731
B71: 15 | C71: =($B71*F41-F61)/C9 -> 1.3657591 | D71: =IF(C71<=0,"N/A",C71^(1/3)-1) -> 0.10949334 | E71: =($B71*G41-G61)/C9 -> 1.4675359 | F71: =IF(E71<=0,"N/A",E71^(1/4)-1) -> 0.1006448 | G71: =($B71*H41-H61)/C9 -> 1.5717798 | H71: =IF(G71<=0,"N/A",G71^(1/5)-1) -> 0.094657713
B72: 16 | C72: =($B72*F41-F61)/C9 -> 1.4608024 | D72: =IF(C72<=0,"N/A",C72^(1/3)-1) -> 0.13465499 | E72: =($B72*G41-G61)/C9 -> 1.5673315 | F72: =IF(E72<=0,"N/A",E72^(1/4)-1) -> 0.11889726 | G72: =($B72*H41-H61)/C9 -> 1.6765651 | H72: =IF(G72<=0,"N/A",G72^(1/5)-1) -> 0.10887881
B73: 17 | C73: =($B73*F41-F61)/C9 -> 1.5558458 | D73: =IF(C73<=0,"N/A",C73^(1/3)-1) -> 0.15874761 | E73: =($B73*G41-G61)/C9 -> 1.667127 | F73: =IF(E73<=0,"N/A",E73^(1/4)-1) -> 0.13629781 | G73: =($B73*H41-H61)/C9 -> 1.7813505 | H73: =IF(G73<=0,"N/A",G73^(1/5)-1) -> 0.12240573
B74: 18 | C74: =($B74*F41-F61)/C9 -> 1.6508892 | D74: =IF(C74<=0,"N/A",C74^(1/3)-1) -> 0.18187798 | E74: =($B74*G41-G61)/C9 -> 1.7669225 | F74: =IF(E74<=0,"N/A",E74^(1/4)-1) -> 0.15293382 | G74: =($B74*H41-H61)/C9 -> 1.8861358 | H74: =IF(G74<=0,"N/A",G74^(1/5)-1) -> 0.13531033
B75: 20 | C75: =($B75*F41-F61)/C9 -> 1.8409759 | D75: =IF(C75<=0,"N/A",C75^(1/3)-1) -> 0.22560175 | E75: =($B75*G41-G61)/C9 -> 1.9665136 | F75: =IF(E75<=0,"N/A",E75^(1/4)-1) -> 0.18419777 | G75: =($B75*H41-H61)/C9 -> 2.0957064 | H75: =IF(G75<=0,"N/A",G75^(1/5)-1) -> 0.15948755
B77: SELLER RETURN — CARLYLE GROUP
B78: Carlyle Entry (Jan 2021, $M) | C78: 530 | D78: Telegraph; Wikipedia; multiple sources
B79: Carlyle Exit (May 2024, $M) | C79: 1136 | D79: PitchBook: Deal Amount $1,136,109K
B80: Holding Period (yrs) | C80: 3.3 | D80: Jan 2021 → May 2024
B81: Implied MOIC | C81: =C79/C78 -> 2.1433962 | D81: Calculated
B82: Implied IRR | C82: =C81^(1/C80)-1 -> 0.25989421 | D82: Calculated
B84: MODELING NOTES
B85: RCF ($28.6M/£22.7M) assumed UNDRAWN in debt schedule. Available for liquidity only. Interest calculated on Term Loan balance only. Standard practice for paper LBO. Carlyle-era group-level debt (CH charges 0004 and 0005) was repaid at the 15-May-2024 close — see Deal Summary rows 96-100 for detail.
B86: Mandatory amortization (1% p.a.) is a paper assumption — no credit agreement terms disclosed. Standard for broadly syndicated leveraged loans.
B87: Cash sweep (50%) is a paper assumption — standard range is 25-75%. Apollo/Oaktree as direct lenders may negotiate different terms.
B88: SONIA rate of 5.20% reflects deal-close rate (May 2024). BoE has since cut rates; forward-looking analysis should consider declining rate environment.
B89: CapEx proxy uses intangible investment (4.5% of rev) since PitchBook shows 0% traditional CapEx. Jagex capitalizes game development costs as intangible assets.
B90: EBITDA margin of 40% uses Pro Forma basis ($75M/$188.8M = 39.7%). Reported FY2024 margin of 19.8% reflects post-acquisition reinvestment, not normalized earning power.
B92: MODELING NOTES (additional)
B93: Lender identities (B13:C16) — Apollo $91.96M, Oaktree $72.19M, Permira (undisclosed) — are sourced to PitchBook reporting. No open-source corroboration in Reorg, Debtwire, FT, Bloomberg, sponsor releases, or Companies House (paid PDF instrument required for primary verification). Marked ILLUSTRATIVE (yellow fill).
B94: SONIA + 600bps pricing (C32:C33) — from PitchBook reporting. UK direct-lender unitranche pricing for similar 2024 deals ranged ~SONIA+550-700bps based on sector reporting; 600bps is a plausible midpoint. Marked ILLUSTRATIVE. Debt schedule uses SONIA at close (5.20% on 14-May-2024 per BoE IUDSOIA) held flat for modeling simplicity; actual 2024 path stepped down to 5.0% (Aug) and 4.70% (Nov) following BoE Bank Rate cuts.
B95: Note on Carlyle-era debt: At the operating company level (Jagex Ltd #03982706), funded debt was zero. At the group level, Carlyle-era acquisition debt was secured under Companies House charges 0004 (Lucid Trustee, May 2021) and 0005 (Kroll Trustee, June 2023), both satisfied 15 May 2024. CVC/Haveli debt (charge 0006, Sep 2024) cascaded from Janus Bidco to opco at close.
B100: MANAGEMENT INCENTIVE PLAN (MIP)
B101: Standard PE deal feature: 8-12% of fully-diluted equity reserved for management sweet equity, with time-vesting plus performance vesting typically gated on sponsor MOIC >= 2.0x. Returns above the hurdle are diluted by the MIP %.
B103: MIP % of fully-diluted equity | C103: 0.1 | D103: Assumption: 10% (industry midpoint). Jon Bellamy CVC-appointed CEO suggests active MIP.
B104: MIP vesting hurdle (Sponsor MOIC) | C104: 2 | D104: Below 2.0x MOIC: MIP = 0. Above: MIP participates pro rata in excess returns.
B105: Reference exit case (for illustration) | C105: 15x Exit EV/EBITDA at Year 5 | D105: Base case; MIP dilution varies by exit multiple — see Section D.
B107: Gross Sponsor Equity Proceeds at 15x Y5 (£M) | C107: =15*H41-H61 -> 1207.1269 | D107: Formula: 15 × Y5 EBITDA − Y5 debt
B108: MIP Dilution Applied (£M) | C108: =MAX(0,(C107-C104*C9)*C103) -> 0 | D108: Pro rata on excess above 2.0x MOIC hurdle
B109: Net Sponsor Equity Proceeds (£M) | C109: =C107-C108 -> 1207.1269
B110: Sponsor MOIC (pre-MIP) | C110: =C107/C9 -> 1.5717798
B111: Sponsor MOIC (post-MIP) | C111: =C109/C9 -> 1.5717798
B112: Sponsor IRR (5yr, post-MIP) | C112: =(C109/C9)^(1/5)-1 -> 0.094657713
B113: MIP dilution impact on MOIC | C113: =C110-C111 -> 0 | D113: Absolute MOIC points lost to MIP
B116: OPERATING SCENARIOS
B117: Three cases: Base (as-built, matches existing operating model), Upside (stronger live-service monetization + successful Dragonwilds franchise extension), Downside (FY24 margin compression proves persistent; revenue growth slows toward UK gaming sector average). Each case shows 5-year projections and sponsor returns at 15x Y5 exit.
B119: Assumption | C119: Base | D119: Upside | E119: Downside | F119: Rationale
...

Sheet Football Field
A1: VALUATION FOOTBALL FIELD — IMPLIED ENTERPRISE VALUE
A2: Summary of all valuation methodologies | Deal Price: $1,136M | FX: 1.2627 GBP/USD (May 2024)
A4: Methodology | B4: Low ($M) | C4: High ($M) | D4: Midpoint ($M) | E4: Deal ($1,136M) | F4: Source / Notes
A5: CCA (EV/EBITDA, PitchBook comps 25th pctl to 75th pctl) | B5: 299 | C5: 933 | D5: =(B5+C5)/2 -> 616 | E5: 1136 | F5: CCA Tab — PitchBook 8 gaming comps, 25th-75th EV/EBITDA (4.0x-12.5x) × $75M PF EBITDA. USD
A6: PTA (EV/EBITDA, PitchBook M&A comps 25th pctl to 75th pctl) | B6: 374 | C6: 1184 | D6: =(B6+C6)/2 -> 779 | E6: 1136 | F6: PTA Tab — PitchBook 6 gaming M&A comps 2021-2025, 25th-75th EV/EBITDA (4.98x-15.79x) × $75M PF EBITDA. USD
A7: DCF (WACC 8.0% - 12.0%, Terminal Growth 1.5% - 3.5%) | B7: 585 | C7: 1293 | D7: =(B7+C7)/2 -> 939 | E7: 1136 | F7: DCF Tab — Sensitivity table: WACC 12%/TGR 1.5% (low) to WACC 8%/TGR 3.5% (high). Converted from £463M-£1,024M at 1.2627
A8: LBO Analysis (Sponsor Returns at 15-18x Exit) | B8: 779 | C8: 1076 | D8: =(B8+C8)/2 -> 927.5 | E8: 1136 | F8: LBO Tab — Range reverse-engineered from the IRR sensitivity table (LBO Model B65:H75): entry prices that yield 15-20% Gross IRR at 15x-18x Exit EV/EBITDA over a 5yr hold. Converted from £617M-£852M at FX 1.2627.
A9: PTA — Live-service / take-private set | B9: =PTA!C71*75 -> 1192.5 | C9: =PTA!C72*75 -> 1515 | D9: =(B9+C9)/2 -> 1353.75 | E9: 1136 | F9: Expanded set: Carlyle/Jagex 2021 + Activision/Zynga/Bungie/Keywords + Codemasters. PTA tab rows 59-64.
A10: DEAL PRICE: $1,136M (~£900M)
A12: Enterprise Value: $1,087M implied EV / $1,136M deal amount | 15.1x Pro Forma EBITDA ($75M)
A13: Deal underwritten at 19.25x Implied EV / Reported EBITDA (20.13x Deal / Reported EBITDA)
A17: CHART DATA (stacked bar: Invisible Base + Range)
A18: Methodology | B18: Low ($M) | C18: High ($M) | D18: Invisible Base | E18: Range (High - Low) | F18: Deal Price
A19: LBO analysis (15% – 20% IRR at 15x – 18x exit) | B19: 779 | C19: 1076 | D19: =B19 -> 779 | E19: =C19-B19 -> 297 | F19: 1136
A20: Discounted cash flow analysis (8.0% – 12.0% WACC) | B20: 585 | C20: 1293 | D20: =B20 -> 585 | E20: =C20-B20 -> 708 | F20: 1136
A21: Precedent transactions analysis (EV / EBITDA) | B21: 374 | C21: 1184 | D21: =B21 -> 374 | E21: =C21-B21 -> 810 | F21: 1136
A22: Comparable companies analysis (EV / EBITDA) | B22: 299 | C22: 933 | D22: =B22 -> 299 | E22: =C22-B22 -> 634 | F22: 1136
A24: CHART VALUES:
A25: CCA: $299M — $933M | PTA: $374M — $1,184M | DCF: $585M — $1,293M | LBO: $779M — $1,076M | Deal: $1,136M
A26: All values converted from £ to $ at 1.2627 GBP/USD (May 2024 average, X-Rates.com) — deal-close FX rate
A28: METHODOLOGY NOTES
A29: Row 9: Live-service / take-private precedent set — uses Microsoft/Activision, Take-Two/Zynga, Sony/Bungie, EQT/Keywords plus the seller precedent (Carlyle/Jagex 2021) plus Codemasters. Median ~19.5x EV/EBITDA × $75M PF EBITDA implies ~$1.46B EV — closer to the deal price than the broader PTA range ($374M-$1,184M).
A30: Row 6 retained for reference. The broader 6-deal PTA understates the implied range because three of the six deals (astragon, Coffee Stain, Thunderful) are small-cap or restructuring transactions not directly comparable to a $1.1B live-service buyout.
A31: No fairness opinion exists for this private-to-private deal. The Football Field serves as the primary cross-method valuation reference. Deal price $1,136M sits at the high end of CCA, near midpoint of the live-service PTA set, and within the DCF range.

Sheet Source Log
B1: SOURCE LOG — ALL DATA CITATIONS
B3: # | C3: Source | D3: Data Points | E3: URL / Reference | F3: Date | G3: Tier
B4: 1 | C4: PitchBook Deal #6 | D4: Deal amount $1.14B, EV $1.09B, PF EBITDA $75M, debt $164.15M, type, status, date, employees, CEO, % acquired | E4: PitchBook Data, Inc. (accessed Apr 2026) | F4: May 2024
B5: 2 | C5: PitchBook Debt Summary | D5: TL $130.63M SONIA+600 7yr mat 13-May-2031; RCF $36.17M SONIA+600 | E5: PitchBook Data, Inc. | F5: May 2024
B6: 3 | C6: PitchBook Investors | D6: CVC Fund VIII (Lead: N.Clarry); Haveli (Lead: B.Sheth) | E6: PitchBook Data, Inc. | F6: Feb 2024
B7: 4 | C7: PitchBook Advisors | D7: GS (CVC+Haveli), Aream/Liberty/MS (Jagex), Apollo/Oaktree (debt), L&W/K&E (legal) | E7: PitchBook Data, Inc. | F7: 2024
B8: 5 | C8: PitchBook Sellers/Exiters | D8: Carlyle full exit $1.14B, CP VII + CETP IV, 100% sold | E8: PitchBook Data, Inc. | F8: 2024
B9: 6 | C9: PitchBook Lenders | D9: Apollo $91.96M, Oaktree $72.19M, Permira (undisclosed) | E9: PitchBook Data, Inc. | F9: 2024
B10: 7 | C10: PitchBook Financials TTM | D10: Rev $188.8M, GP $161.3M, EBITDA $56.4M, EBIT $47.4M, NI $48.9M, BS full | E10: PitchBook Data, Inc. (TTM Dec 2023) | F10: 2024
B11: 8 | C11: PitchBook Deal Multiples | D11: EV/EBITDA 19.25x, EV/Rev 5.76x, Deal/EBITDA 20.13x, Debt/EBITDA 2.91x | E11: PitchBook Data, Inc. | F11: 2024
B12: 9 | C12: PitchBook Ratios | D12: EBITDA margin 29.90%, rev growth 10.51%, current ratio 2.63x | E12: PitchBook Data, Inc. | F12: 2024
B13: 10 | C13: Carlyle PR | D13: Deal overview, advisors, subs 2.4M, employees 700 | E13: carlyle.com | F13: Feb 9 2024
B14: 11 | C14: CVC PR | D14: Deal confirmation, franchise details | E14: cvc.com | F14: Feb 9 2024
B15: 12 | C15: Jagex PR | D15: Deal confirmation, record subs, $1.5B lifetime rev | E15: jagex.com | F15: Feb 9 2024
... B31: 28 | C31: PitchBook M&A Comps (PTA) | D31: Sybo, Codemasters, Climax, astragon, Coffee Stain, Thunderful — EV/EBITDA & EV/Rev multiples | E31: PitchBook Data, Inc. (MnA Comps Tab) | F31: Apr 15 2026
B33: PRIMARY SOURCES (Tier 1 — Companies House)
B34: 29 | C34: Companies House — Jagex Ltd (#03982706) | D34: FY2023 accounts (filed 13-Mar-2025), FY2024 accounts (filed 4-Jun-2025), FY2022 accounts (filed 4-Apr-2024) | E34: https://find-and-update.company-information.service.gov.uk/company/03982706/filing-history | F34: Apr 2024 - Jun 2025 | G34: Tier 1
B35: 30 | C35: Companies House — Jagex Charges Register | D35: Charge 0004 (Lucid 7-May-2021, satisfied 15-May-2024); Charge 0005 (Kroll 20-Jun-2023, satisfied); Charge 0006 (Kroll 10-Sep-2024, outstanding) | E35: https://find-and-update.company-information.service.gov.uk/company/03982706/charges | F35: May 2021 - Sep 2024 | G35: Tier 1
B36: 31 | C36: Companies House — Janus Bidco Limited (#15451932) | D36: Inc. 30-Jan-2024; MR01 charge created 25-Apr-2024 (40pp); SH01 share allotment 14-May-2024 in USD; consolidated FY24 accounts filed 7-Oct-2025 (75pp) | E36: https://find-and-update.company-information.service.gov.uk/company/15451932/filing-history | F36: Jan 2024 - Oct 2025 | G36: Tier 1
B37: 32 | C37: Companies House — Janus Midco Limited (#15451988) | D37: Intermediate holdco; Inc. 30-Jan-2024 | E37: https://find-and-update.company-information.service.gov.uk/company/15451988 | F37: Jan 2024 | G37: Tier 1
B38: 33 | C38: Companies House — Janus UK Topco Ltd (FC041396, Jersey) | D38: Inc. 13-Mar-2024; directors Lambkin & Motajo | E38: North Data: northdata.com/Janus+UK+Topco+Ltd | F38: Mar 2024 | G38: Tier 1
B39: 34 | C39: Carlyle Group press release — Jagex sale | D39: Deal announcement; advisors Morgan Stanley + Aream & Co (sell-side); Goldman (buy-side); Carlyle Partners VII + CETP IV; "Terms not disclosed" | E39: https://www.carlyle.com/media-room/news-release-archive/carlyle-agrees-to-sell-jagex-to-cvc-capital-partners-and-haveli | F39: 9-Feb-2024 | G39: Tier 2
B40: 35 | C40: CVC Capital Partners press release | D40: Deal confirmation; Fund VIII; "20+ year history of leadership in live service gaming" | E40: https://www.cvc.com/media/news/2024/2024-02-09-carlyle-agrees-to-sell-jagex-to-cvc-capital-partners-and-haveli-investments/ | F40: 9-Feb-2024 | G40: Tier 2
B41: 36 | C41: Carlyle Group press release — 2021 Jagex acquisition | D41: Carlyle's entry; CP VII + CETP IV equity sources; deal price NOT disclosed in Carlyle press release. $530M entry used in model is Macarthur Fortune's 2020 price as flat-hold proxy (see row 42). | E41: https://www.carlyle.com/media-room/news-release-archive/carlyle-group-acquires-jagex-leading-online-video-game-company-and | F41: 25-Jan-2021 | G41: Tier 2
B42: 37 | C42: Macarthur Fortune Holding LLC press release | D42: Acquisition of Jagex by Macarthur Fortune from Shanghai Hongtou / Shanghai Fukong for $530M — CONFIRMED (this is the 2020 deal, not Carlyle 2021). Carlyle's January 2021 price was never officially disclosed; $530M used as flat-hold proxy. | E42: https://www.prnewswire.com/news-releases/platinum-fortune-acquires-jagex-for-530-million-301050848.html | F42: 1-May-2020 | G42: Tier 2
B43: 38 | C43: Latham & Watkins (CVC counsel) | D43: Deal counsel team; Suneel Basson-Bhatoa (corporate); finance partners team confirms debt was raised | E43: https://www.lw.com/en/news/2024/02/latham-advises-cvc-capital-partners-on-the-acquisition-of-jagex | F43: Feb 2024 | G43: Tier 2
B44: 39 | C44: Kirkland & Ellis (Carlyle counsel) | D44: Deal counsel team; David Higgins (corporate); Jerome Hoyle (debt finance — confirms repayment workstream) | E44: https://www.kirkland.com/news/press-release/2024/02/kirkland-advises-carlyle-on-sale-of-jagex | F44: Feb 2024 | G44: Tier 2
B45: 40 | C45: Kirkland & Ellis — 2021 Jagex acquisition counsel | D45: Carlyle 2021 acquisition legal team | E45: https://www.kirkland.com/news/press-release/2021/01/kirkland-represents-the-carlyle-group-on-jagex | F45: Jan 2021 | G45: Tier 2
... B53: 48 | C53: Newzoo PC & Console Gaming Report 2024 | D53: 67% PC player-hours on titles ≥6 years old; live-service / GaaS market context | E53: newzoo.com/resources/trend-reports | F53: 2024 | G53: Tier 3
B56: SOURCE TIER LEGEND
B57: Tier 1 (definitive): SEC filings, Companies House full audited accounts, regulatory filings | Tier 2 (authoritative): Sponsor PRs, banker fairness opinions, rating agency reports, IR materials | Tier 3 (high-quality secondary): FT/Bloomberg/Reuters/WSJ deal reporting, PitchBook, Mergermarket | Tier 4 (with caution): Trade press (PE Insights, GamesIndustry.biz, Telegraph) | Tier 5 (contextual): Wikipedia, Crunchbase, blog posts
